{
    "{\"element_url\":\"/\",\"elementClasses\":\"rewardHolder\",\"elementId\":\"\",\"elementText\":\"-RAND-\",\"dataanalyticsID\":\"null\"}":1074460,
    "{\"element_url\":\"/\",\"elementClasses\":\"\",\"elementId\":\"\",\"elementText\":\"สมัครสมาชิก\",\"dataanalyticsID\":\"null\"}":1074462,
    "{\"element_url\":\"/\",\"elementClasses\":\"rewardText\",\"elementId\":\"\",\"elementText\":\"-RAND-\",\"dataanalyticsID\":\"null\"}":1074463,
    "{\"element_url\":\"/\",\"elementClasses\":\"label\",\"elementId\":\"\",\"elementText\":\"โปรโมชั่น\",\"dataanalyticsID\":\"null\"}":1074464,
    "{\"element_url\":\"/promotions\",\"elementClasses\":\"\",\"elementId\":\"\",\"elementText\":\"โปรโมชั่น\",\"dataanalyticsID\":\"null\"}":1074465,
    "{\"element_url\":\"/\",\"elementClasses\":\"\",\"elementId\":\"\",\"elementText\":\"ยืนยันความถูกต้อง\",\"dataanalyticsID\":\"null\"}":1074470,
    "{\"element_url\":\"/\",\"elementClasses\":\"v-icon%20mdi%20mdi-gift%20theme--dark\",\"elementId\":\"\",\"elementText\":\"\",\"dataanalyticsID\":\"null\"}":1074471,
    "{\"element_url\":\"/\",\"elementClasses\":\"demoBtn\",\"elementId\":\"\",\"elementText\":\"หรือลองดูตัวอย่าง\",\"dataanalyticsID\":\"null\"}":1074475,
    "{\"element_url\":\"/\",\"elementClasses\":\"jwbtn%20jwbtn-green\",\"elementId\":\"\",\"elementText\":\"ยืนยันความถูกต้อง\",\"dataanalyticsID\":\"null\"}":1074477,
    "{\"element_url\":\"/SignUp\",\"elementClasses\":\"\",\"elementId\":\"\",\"elementText\":\"สมัครสมาชิก\",\"dataanalyticsID\":\"null\"}":1074483,
    "{\"element_url\":\"/\",\"elementClasses\":\"label\",\"elementId\":\"\",\"elementText\":\"More\",\"dataanalyticsID\":\"null\"}":1074484,
    "{\"element_url\":\"/quick\",\"elementClasses\":\"\",\"elementId\":\"\",\"elementText\":\"More\",\"dataanalyticsID\":\"null\"}":1074485,
    "{\"element_url\":\"/\",\"elementClasses\":\"balance%20font-size%20fontType-2\",\"elementId\":\"\",\"elementText\":\"-RAND-\",\"dataanalyticsID\":\"null\"}":1074487,
    "{\"element_url\":\"/\",\"elementClasses\":\"copy-text\",\"elementId\":\"\",\"elementText\":\"คัดลอกลิงค์\",\"dataanalyticsID\":\"null\"}":1074490,
    "{\"element_url\":\"/\",\"elementClasses\":\"_hj-1uQd9__MinimizedWidgetMiddle__text\",\"elementId\":\"\",\"elementText\":\"Feedback\",\"dataanalyticsID\":\"null\"}":1074491,
    "{\"element_url\":\"/\",\"elementClasses\":\"_hj-CoyQX__styles__iconX%20_hj-3e6MN__styles__icon\",\"elementId\":\"\",\"elementText\":\"\",\"dataanalyticsID\":\"null\"}":1074492,
    "{\"element_url\":\"/\",\"elementClasses\":\"playBtn\",\"elementId\":\"\",\"elementText\":\"เล่นจริง\",\"dataanalyticsID\":\"null\"}":1074493,
    "{\"element_url\":\"/\",\"elementClasses\":\"v-icon%20icon%20icon-jw-money%20theme--dark\",\"elementId\":\"\",\"elementText\":\"\",\"dataanalyticsID\":\"null\"}":1074497,
    "{\"element_url\":\"/\",\"elementClasses\":\"v-icon%20mdi%20mdi-menu%20theme--dark\",\"elementId\":\"\",\"elementText\":\"\",\"dataanalyticsID\":\"null\"}":1074504,
    "{\"element_url\":\"/\",\"elementClasses\":\"game-image-holder\",\"elementId\":\"\",\"elementText\":\"PG%20เล่นจริง%20Journey%20to%20the%20Wealth\",\"dataanalyticsID\":\"null\"}":1074506,
    "{\"element_url\":\"/\",\"elementClasses\":\"loader-overlay%20dark\",\"elementId\":\"\",\"elementText\":\"\",\"dataanalyticsID\":\"null\"}":1074509,
    "{\"element_url\":\"/\",\"elementClasses\":\"\",\"elementId\":\"\",\"elementText\":\"เข้าสู่ระบบ\",\"dataanalyticsID\":\"null\"}":1074511,
    "{\"element_url\":\"/\",\"elementClasses\":\"\",\"elementId\":\"\",\"elementText\":\"\",\"dataanalyticsID\":\"null\"}":1074513,
    "{\"element_url\":\"/\",\"elementClasses\":\"v-input--selection-controls__ripple\",\"elementId\":\"\",\"elementText\":\"\",\"dataanalyticsID\":\"null\"}":1074515,
    "{\"element_url\":\"/\",\"elementClasses\":\"v-icon%20closeBtn%20v-icon--link%20mdi%20mdi-close-circle-outline%20theme--dark\",\"elementId\":\"\",\"elementText\":\"\",\"dataanalyticsID\":\"null\"}":1074517,
    "{\"element_url\":\"/\",\"elementClasses\":\"v-icon%20v-icon--link%20mdi%20mdi-eye-off%20theme--dark%20primary--text\",\"elementId\":\"\",\"elementText\":\"\",\"dataanalyticsID\":\"null\"}":1074518,
    "{\"element_url\":\"/Crypto\",\"elementClasses\":\"\",\"elementId\":\"\",\"elementText\":\"Crypto\",\"dataanalyticsID\":\"null\"}":1074528,
    "{\"element_url\":\"/\",\"elementClasses\":\"\",\"elementId\":\"\",\"elementText\":\"-RAND-\",\"dataanalyticsID\":\"null\"}":1074532,
    "{\"element_url\":\"/\",\"elementClasses\":\"\",\"elementId\":\"\",\"elementText\":\"ฝากเงิน\",\"dataanalyticsID\":\"null\"}":1074534,
    "{\"element_url\":\"/\",\"elementClasses\":\"loader-overlay\",\"elementId\":\"\",\"elementText\":\"\",\"dataanalyticsID\":\"null\"}":1074538,
    "{\"element_url\":\"/\",\"elementClasses\":\"v-icon%20v-icon--link%20mdi%20mdi-close%20theme--dark\",\"elementId\":\"\",\"elementText\":\"\",\"dataanalyticsID\":\"null\"}":1074544,
    "{\"element_url\":\"/\",\"elementClasses\":\"username\",\"elementId\":\"\",\"elementText\":\"-ACCOUNT-\",\"dataanalyticsID\":\"null\"}":1074548,
    "{\"element_url\":\"/\",\"elementClasses\":\"balanceHolder\",\"elementId\":\"\",\"elementText\":\"-RAND-\",\"dataanalyticsID\":\"null\"}":1074552,
    "{\"element_url\":\"/\",\"elementClasses\":\"v-icon%20v-icon--link%20mdi%20mdi-eye-off%20theme--dark\",\"elementId\":\"\",\"elementText\":\"\",\"dataanalyticsID\":\"null\"}":1074559,
    "{\"element_url\":\"/\",\"elementClasses\":\"v-input__slot\",\"elementId\":\"\",\"elementText\":\"ชื่อ-นามสกุล\",\"dataanalyticsID\":\"null\"}":1074585,
    "{\"element_url\":\"/\",\"elementClasses\":\"loginModal-wrapper\",\"elementId\":\"\",\"elementText\":\"เข้าสู่ระบบ%20ชื่อผู้ใช้%20รหัสผ่าน%20check_box%20จดจำฉัน%20เข้าสู่ระบบ%20ยังไม่เป็นสมาชิก?%20สมัครสมาชิก%20ลืมรหัสผ่าน?\",\"dataanalyticsID\":\"null\"}":1074587,
    "{\"element_url\":\"/\",\"elementClasses\":\"jwbtn%20jwbtn-primary-transparent%20signup-button\",\"elementId\":\"\",\"elementText\":\"สมัครสมาชิก\",\"dataanalyticsID\":\"null\"}":1074588,
    "{\"element_url\":\"/\",\"elementClasses\":\"v-icon%20iconRefresh%20mdi%20mdi-cached%20theme--dark\",\"elementId\":\"\",\"elementText\":\"\",\"dataanalyticsID\":\"null\"}":1074590,
    "{\"element_url\":\"/\",\"elementClasses\":\"tab\",\"elementId\":\"\",\"elementText\":\"More\",\"dataanalyticsID\":\"null\"}":1074599,
    "{\"element_url\":\"/\",\"elementClasses\":\"v-icon%20icon%20icon-jw-slot%20theme--dark\",\"elementId\":\"\",\"elementText\":\"\",\"dataanalyticsID\":\"null\"}":1074608,
    "{\"element_url\":\"/Slots\",\"elementClasses\":\"\",\"elementId\":\"\",\"elementText\":\"สล็อต\",\"dataanalyticsID\":\"null\"}":1074609,
    "{\"element_url\":\"/\",\"elementClasses\":\"\",\"elementId\":\"\",\"elementText\":\"ฟรี\",\"dataanalyticsID\":\"null\"}":1074613,
    "{\"element_url\":\"/\",\"elementClasses\":\"\",\"elementId\":\"\",\"elementText\":\"บ้าน\",\"dataanalyticsID\":\"null\"}":1074623,
    "{\"element_url\":\"/\",\"elementClasses\":\"v-icon%20eventMessgaeIcon%20mdi%20mdi-bell-ring-outline%20theme--dark%20animate\",\"elementId\":\"\",\"elementText\":\"\",\"dataanalyticsID\":\"null\"}":1074624,
    "{\"element_url\":\"/\",\"elementClasses\":\"text\",\"elementId\":\"\",\"elementText\":\"ระบบประกาศ\",\"dataanalyticsID\":\"null\"}":1074626,
    "{\"element_url\":\"/\",\"elementClasses\":\"jwbtn%20jwbtn-primary-transparent%20jw-text\",\"elementId\":\"\",\"elementText\":\"เข้าสู่ระบบ\",\"dataanalyticsID\":\"null\"}":1074631,
    "{\"element_url\":\"/\",\"elementClasses\":\"balanceText\",\"elementId\":\"\",\"elementText\":\"-RAND-\",\"dataanalyticsID\":\"null\"}":1074637,
    "{\"element_url\":\"/\",\"elementClasses\":\"\",\"elementId\":\"\",\"elementText\":\"สล็อต\",\"dataanalyticsID\":\"null\"}":1074639,
    "{\"element_url\":\"/\",\"elementClasses\":\"content-header\",\"elementId\":\"\",\"elementText\":\"สร้างบัญชีบน%20Siam99%20เพื่อเล่นเกมออนไลน์ที่น่าตื่นเต้นทั้งหมด%20ไม่มีข้อจำกัด%20ฟรี%20กรุณากรอกแบบฟอร์มสมัรสมาชิกด้านล่าง\",\"dataanalyticsID\":\"null\"}":1074644,
    "{\"element_url\":\"/quick\",\"elementClasses\":\"nuxt-link-exact-active%20nuxt-link-active\",\"elementId\":\"\",\"elementText\":\"More\",\"dataanalyticsID\":\"null\"}":1074650,
    "{\"element_url\":\"/\",\"elementClasses\":\"vdatetime\",\"elementId\":\"\",\"elementText\":\"\",\"dataanalyticsID\":\"null\"}":1074670,
    "{\"element_url\":\"/\",\"elementClasses\":\"jwbtn%20jwbtn-primary\",\"elementId\":\"\",\"elementText\":\"เข้าสู่ระบบ\",\"dataanalyticsID\":\"null\"}":1074682,
    "{\"element_url\":\"/\",\"elementClasses\":\"tab\",\"elementId\":\"\",\"elementText\":\"บ้าน\",\"dataanalyticsID\":\"null\"}":1074684,
    "{\"element_url\":\"/\",\"elementClasses\":\"form-content\",\"elementId\":\"\",\"elementText\":\"ชื่อผู้ใช้%20รหัสผ่าน%20ยืนยันรหัสผ่าน%20ชื่อ-นามสกุล%20อีเมล%20เบอร์มือถือ%20รหัสรักษาความปลอดภัย%20สมัครสมาชิก\",\"dataanalyticsID\":\"null\"}":1074688,
    "{\"element_url\":\"/v2/SI/PictureLanguage.204.4\",\"elementClasses\":\"swiper-lazy%20swiper-lazy-loaded\",\"elementId\":\"\",\"elementText\":\"\",\"dataanalyticsID\":\"null\"}":1074706,
    "{\"element_url\":\"/\",\"elementClasses\":\"\",\"elementId\":\"\",\"elementText\":\"ดำเนินการต่อเพื่อเล่นเกม\",\"dataanalyticsID\":\"null\"}":1074754,
    "{\"element_url\":\"/\",\"elementClasses\":\"\",\"elementId\":\"\",\"elementText\":\"คัดลอกลิงค์\",\"dataanalyticsID\":\"null\"}":1074760,
    "{\"element_url\":\"/\",\"elementClasses\":\"toolbar-logo\",\"elementId\":\"\",\"elementText\":\"\",\"dataanalyticsID\":\"null\"}":1074772,
    "{\"element_url\":\"/\",\"elementClasses\":\"v-tabs__item\",\"elementId\":\"\",\"elementText\":\"ฟรีเครดิต\",\"dataanalyticsID\":\"null\"}":1074789,
    "{\"element_url\":\"/\",\"elementClasses\":\"v-tabs__item%20v-tabs__item--active\",\"elementId\":\"\",\"elementText\":\"ฟรีเครดิต\",\"dataanalyticsID\":\"null\"}":1074790,
    "{\"element_url\":\"/\",\"elementClasses\":\"v-tabs__item\",\"elementId\":\"\",\"elementText\":\"ฝาก\",\"dataanalyticsID\":\"null\"}":1074791,
    "{\"element_url\":\"/\",\"elementClasses\":\"v-tabs__item%20v-tabs__item--active\",\"elementId\":\"\",\"elementText\":\"ฝาก\",\"dataanalyticsID\":\"null\"}":1074792,
    "{\"element_url\":\"/\",\"elementClasses\":\"v-tabs__item%20v-tabs__item--active\",\"elementId\":\"\",\"elementText\":\"กีฬา\",\"dataanalyticsID\":\"null\"}":1074794,
    "{\"element_url\":\"/\",\"elementClasses\":\"v-tabs__item\",\"elementId\":\"\",\"elementText\":\"คาสิโนสด\",\"dataanalyticsID\":\"null\"}":1074795,
    "{\"element_url\":\"/\",\"elementClasses\":\"v-tabs__item%20v-tabs__item--active\",\"elementId\":\"\",\"elementText\":\"คาสิโนสด\",\"dataanalyticsID\":\"null\"}":1074796,
    "{\"element_url\":\"/v2/SI/PromotionInfoLanguage3440\",\"elementClasses\":\"\",\"elementId\":\"\",\"elementText\":\"\",\"dataanalyticsID\":\"null\"}":1074797,
    "{\"element_url\":\"/\",\"elementClasses\":\"v-icon%20mdi%20mdi-content-copy%20theme--dark\",\"elementId\":\"\",\"elementText\":\"\",\"dataanalyticsID\":\"null\"}":1074818,
    "{\"element_url\":\"/\",\"elementClasses\":\"\",\"elementId\":\"\",\"elementText\":\"อื่นๆ\",\"dataanalyticsID\":\"null\"}":1074819,
    "{\"element_url\":\"/Other-Games\",\"elementClasses\":\"\",\"elementId\":\"\",\"elementText\":\"อื่นๆ\",\"dataanalyticsID\":\"null\"}":1074820,
    "{\"element_url\":\"/\",\"elementClasses\":\"jwbtn%20jwbtn-white%20copy-link\",\"elementId\":\"\",\"elementText\":\"คัดลอกลิงค์\",\"dataanalyticsID\":\"null\"}":1074825,
    "{\"element_url\":\"/\",\"elementClasses\":\"navText\",\"elementId\":\"\",\"elementText\":\"ชนะสปิน\",\"dataanalyticsID\":\"null\"}":1074850,
    "{\"element_url\":\"/Sports\",\"elementClasses\":\"\",\"elementId\":\"\",\"elementText\":\"กีฬา\",\"dataanalyticsID\":\"null\"}":1074861,
    "{\"element_url\":\"/\",\"elementClasses\":\"\",\"elementId\":\"\",\"elementText\":\"ตัวอย่าง:\",\"dataanalyticsID\":\"null\"}":1074866,
    "{\"element_url\":\"/\",\"elementClasses\":\"low-balance-holder\",\"elementId\":\"\",\"elementText\":\"ยอดเงินของคุณดูเหมือนจะเหลือน้อย\",\"dataanalyticsID\":\"null\"}":1074892,
    "{\"element_url\":\"/\",\"elementClasses\":\"v-icon%20v-icon--link%20mdi%20mdi-eye%20theme--dark%20primary--text\",\"elementId\":\"\",\"elementText\":\"\",\"dataanalyticsID\":\"null\"}":1074921,
    "{\"element_url\":\"/\",\"elementClasses\":\"input-helper\",\"elementId\":\"\",\"elementText\":\"ชื่อ-นามสกุล\",\"dataanalyticsID\":\"null\"}":1074922,
    "{\"element_url\":\"/\",\"elementClasses\":\"v-icon%20mdi%20mdi-home%20theme--dark\",\"elementId\":\"\",\"elementText\":\"\",\"dataanalyticsID\":\"null\"}":1074926,
    "{\"element_url\":\"/SignUp\",\"elementClasses\":\"signUp\",\"elementId\":\"\",\"elementText\":\"สมัครสมาชิก\",\"dataanalyticsID\":\"null\"}":1074936,
    "{\"element_url\":\"/\",\"elementClasses\":\"label\",\"elementId\":\"\",\"elementText\":\"ฝาก\",\"dataanalyticsID\":\"null\"}":1074957,
    "{\"element_url\":\"/\",\"elementClasses\":\"v-input__slot\",\"elementId\":\"\",\"elementText\":\"ชื่อผู้ใช้\",\"dataanalyticsID\":\"null\"}":1074959,
    "{\"element_url\":\"/\",\"elementClasses\":\"v-icon%20v-icon--link%20mdi%20mdi-eye%20theme--dark\",\"elementId\":\"\",\"elementText\":\"\",\"dataanalyticsID\":\"null\"}":1075007,
    "{\"element_url\":\"/\",\"elementClasses\":\"phoneNumber%20fontType-2\",\"elementId\":\"\",\"elementText\":\"\",\"dataanalyticsID\":\"null\"}":1075024,
    "{\"element_url\":\"/\",\"elementClasses\":\"forgotPassword\",\"elementId\":\"\",\"elementText\":\"ลืมรหัสผ่าน?\",\"dataanalyticsID\":\"null\"}":1075042,
    "{\"element_url\":\"/\",\"elementClasses\":\"forgotModal-wrapper\",\"elementId\":\"\",\"elementText\":\"ลืมรหัสผ่าน%20ชื่อผู้ใช้%20login.forgotPass.notify.p%20radio_button_checked%20login.forgotPass.notify.email%20radio_button_unchecked%20login.forgotPass.notify.sms%20อีเมล%20รหัสผ้องกัน%20ยืนยัน\",\"dataanalyticsID\":\"null\"}":1075043,
    "{\"element_url\":\"/\",\"elementClasses\":\"v-icon%20v-icon--link%20mdi%20mdi-account%20theme--dark%20primary--text\",\"elementId\":\"\",\"elementText\":\"\",\"dataanalyticsID\":\"null\"}":1075112,
    "{\"element_url\":\"/\",\"elementClasses\":\"flex%20xs12%20sm6\",\"elementId\":\"\",\"elementText\":\"ยืนยันรหัสผ่าน\",\"dataanalyticsID\":\"null\"}":1075129,
    "{\"element_url\":\"/\",\"elementClasses\":\"primaryToolbar\",\"elementId\":\"\",\"elementText\":\"เข้าสู่ระบบ%20สมัครสมาชิก%20TH\",\"dataanalyticsID\":\"null\"}":1075132,
    "{\"element_url\":\"/Messages\",\"elementClasses\":\"\",\"elementId\":\"\",\"elementText\":\"ข่าวสาร\",\"dataanalyticsID\":\"null\"}":1075212,
    "{\"element_url\":\"/\",\"elementClasses\":\"form-wrapper\",\"elementId\":\"\",\"elementText\":\"ชื่อผู้ใช้%20รหัสผ่าน%20ยืนยันรหัสผ่าน%20ชื่อ-นามสกุล%20อีเมล%20เบอร์มือถือ%20รหัสรักษาความปลอดภัย%20สมัครสมาชิก\",\"dataanalyticsID\":\"null\"}":1075231,
    "{\"element_url\":\"/\",\"elementClasses\":\"v-input__slot\",\"elementId\":\"\",\"elementText\":\"รหัสผ่าน\",\"dataanalyticsID\":\"null\"}":1075233,
    "{\"element_url\":\"/\",\"elementClasses\":\"v-input%20rememberMe%20v-input--selection-controls%20v-input--checkbox%20theme--dark\",\"elementId\":\"\",\"elementText\":\"check_box_outline_blank%20จดจำฉัน\",\"dataanalyticsID\":\"null\"}":1075289,
    "{\"element_url\":\"/\",\"elementClasses\":\"v-icon%20icon%20icon-jw-line%20theme--dark\",\"elementId\":\"\",\"elementText\":\"\",\"dataanalyticsID\":\"null\"}":1075290,
    "{\"element_url\":\"/\",\"elementClasses\":\"v-text-field__slot\",\"elementId\":\"\",\"elementText\":\"ชื่อผู้ใช้\",\"dataanalyticsID\":\"null\"}":1075296,
    "{\"element_url\":\"/\",\"elementClasses\":\"label\",\"elementId\":\"\",\"elementText\":\"บ้าน\",\"dataanalyticsID\":\"null\"}":1075301,
    "{\"element_url\":\"/\",\"elementClasses\":\"v-overlay%20v-overlay--active\",\"elementId\":\"\",\"elementText\":\"\",\"dataanalyticsID\":\"null\"}":1075306,
    "{\"element_url\":\"/\",\"elementClasses\":\"nuxt-link-exact-active%20nuxt-link-active\",\"elementId\":\"\",\"elementText\":\"บ้าน\",\"dataanalyticsID\":\"null\"}":1075352,
    "{\"element_url\":\"/v2/SI/PromotionInfoLanguage4040\",\"elementClasses\":\"\",\"elementId\":\"\",\"elementText\":\"\",\"dataanalyticsID\":\"null\"}":1075365,
    "{\"element_url\":\"/\",\"elementClasses\":\"game-image-holder\",\"elementId\":\"\",\"elementText\":\"PG%20เล่นจริง%20Caishen%20Wins\",\"dataanalyticsID\":\"null\"}":1075370,
    "{\"element_url\":\"/\",\"elementClasses\":\"\",\"elementId\":\"\",\"elementText\":\"เล่นเพื่อความสนุก\",\"dataanalyticsID\":\"null\"}":1075371,
    "{\"element_url\":\"/\",\"elementClasses\":\"game-image-holder\",\"elementId\":\"\",\"elementText\":\"FC%20เล่นจริง%20NIGHT%20MARKET\",\"dataanalyticsID\":\"null\"}":1075372,
    "{\"element_url\":\"/\",\"elementClasses\":\"game-action%20gameActionIcon\",\"elementId\":\"\",\"elementText\":\"เล่นจริง\",\"dataanalyticsID\":\"null\"}":1075373,
    "{\"element_url\":\"/pn/sw/prod/platform/icon/v2/PG/icon_1629873160042.png\",\"elementClasses\":\"platformIcon\",\"elementId\":\"\",\"elementText\":\"\",\"dataanalyticsID\":\"null\"}":1075374,
    "{\"element_url\":\"/\",\"elementClasses\":\"game-image-holder\",\"elementId\":\"\",\"elementText\":\"PG%20เล่นจริง%20Leprechaun%20Riches\",\"dataanalyticsID\":\"null\"}":1075375,
    "{\"element_url\":\"/\",\"elementClasses\":\"v-icon%20icon%20icon-jw-table%20theme--dark\",\"elementId\":\"\",\"elementText\":\"\",\"dataanalyticsID\":\"null\"}":1075377,
    "{\"element_url\":\"/\",\"elementClasses\":\"header-2\",\"elementId\":\"\",\"elementText\":\"ไม่มีข้อจำกัด%20ฟรี\",\"dataanalyticsID\":\"null\"}":1075395,
    "{\"element_url\":\"/\",\"elementClasses\":\"game-image-holder\",\"elementId\":\"\",\"elementText\":\"PG%20เล่นจริง%20Majestic%20Treasures\",\"dataanalyticsID\":\"null\"}":1075398,
    "{\"element_url\":\"/\",\"elementClasses\":\"tab\",\"elementId\":\"\",\"elementText\":\"ฝาก\",\"dataanalyticsID\":\"null\"}":1075502,
    "{\"element_url\":\"/\",\"elementClasses\":\"v-icon%20mdi%20mdi-settings%20theme--dark\",\"elementId\":\"\",\"elementText\":\"\",\"dataanalyticsID\":\"null\"}":1075518,
    "{\"element_url\":\"/\",\"elementClasses\":\"v-icon%20iconRefresh%20mdi%20mdi-cached%20theme--dark%20rotate\",\"elementId\":\"\",\"elementText\":\"\",\"dataanalyticsID\":\"null\"}":1075532,
    "{\"element_url\":\"/\",\"elementClasses\":\"container%20gameListWrapper%20grid-list-cs\",\"elementId\":\"\",\"elementText\":\"\",\"dataanalyticsID\":\"null\"}":1075570,
    "{\"element_url\":\"/\",\"elementClasses\":\"lowBalance\",\"elementId\":\"\",\"elementText\":\"-RAND-\",\"dataanalyticsID\":\"null\"}":1075621,
    "{\"element_url\":\"/\",\"elementClasses\":\"game-image-holder\",\"elementId\":\"\",\"elementText\":\"JDB%20เล่นจริง%20หรือลองดูตัวอย่าง%20SuperNiubiDeluxe\",\"dataanalyticsID\":\"null\"}":1075626,
    "{\"element_url\":\"/\",\"elementClasses\":\"game-info\",\"elementId\":\"\",\"elementText\":\"Wild%20Bandito\",\"dataanalyticsID\":\"null\"}":1075662,
    "{\"element_url\":\"/\",\"elementClasses\":\"v-icon%20fav-icon%20gameActionIcon%20v-icon--link%20mdi%20mdi-heart-outline%20theme--dark\",\"elementId\":\"\",\"elementText\":\"\",\"dataanalyticsID\":\"null\"}":1075679,
    "{\"element_url\":\"/\",\"elementClasses\":\"game-image-holder\",\"elementId\":\"\",\"elementText\":\"JILI%20เล่นจริง%20FortunePig\",\"dataanalyticsID\":\"null\"}":1075685,
    "{\"element_url\":\"/\",\"elementClasses\":\"\",\"elementId\":\"\",\"elementText\":\"หมุนเดี๋ยวนี้\",\"dataanalyticsID\":\"null\"}":1075692,
    "{\"element_url\":\"/\",\"elementClasses\":\"v-icon%20mdi%20mdi-close%20theme--dark\",\"elementId\":\"\",\"elementText\":\"\",\"dataanalyticsID\":\"null\"}":1075695,
    "{\"element_url\":\"/\",\"elementClasses\":\"v-icon%20mdi%20mdi-chat-processing%20theme--dark\",\"elementId\":\"\",\"elementText\":\"\",\"dataanalyticsID\":\"null\"}":1075704,
    "{\"element_url\":\"/\",\"elementClasses\":\"\",\"elementId\":\"\",\"elementText\":\"เกมตกปลา\",\"dataanalyticsID\":\"null\"}":1075723,
    "{\"element_url\":\"/Fish-Games\",\"elementClasses\":\"\",\"elementId\":\"\",\"elementText\":\"เกมตกปลา\",\"dataanalyticsID\":\"null\"}":1075724,
    "{\"element_url\":\"/\",\"elementClasses\":\"\",\"elementId\":\"\",\"elementText\":\"แบ่งปันลิงค์แนะนำกับเพื่อนของคุณ%20คุณทั้งคู่จะได้รับโบนัสเมื่อเพื่อนของคุณสมัครโดยใช้ลิงค์ของคุณและฝากเงิน%20500%20บาท%20นอกจากนี้ยังสามารถรับเงินคืนได้ไม่จำกัด%20-RAND-%%20จากการเดิมพันของเพื่อนของคุณ!\",\"dataanalyticsID\":\"null\"}":1075765,
    "{\"element_url\":\"/Casino-Live\",\"elementClasses\":\"\",\"elementId\":\"\",\"elementText\":\"คาสิโนสด\",\"dataanalyticsID\":\"null\"}":1075767,
    "{\"element_url\":\"/\",\"elementClasses\":\"game-image-holder\",\"elementId\":\"\",\"elementText\":\"HOTG%20เล่นจริง%20หรือลองดูตัวอย่าง%20lobby\",\"dataanalyticsID\":\"null\"}":1075778,
    "{\"element_url\":\"/\",\"elementClasses\":\"v-messages%20theme--dark\",\"elementId\":\"\",\"elementText\":\"\",\"dataanalyticsID\":\"null\"}":1075799,
    "{\"element_url\":\"/promotions\",\"elementClasses\":\"nuxt-link-exact-active%20nuxt-link-active\",\"elementId\":\"\",\"elementText\":\"โปรโมชั่น\",\"dataanalyticsID\":\"null\"}":1075820,
    "{\"element_url\":\"/pn/sw/prod/platform/icon/v2/AW/icon_1629874625614.png\",\"elementClasses\":\"platformIcon\",\"elementId\":\"\",\"elementText\":\"\",\"dataanalyticsID\":\"null\"}":1075856,
    "{\"element_url\":\"/v2/SI/PromotionInfoLanguage4540\",\"elementClasses\":\"\",\"elementId\":\"\",\"elementText\":\"\",\"dataanalyticsID\":\"null\"}":1075882,
    "{\"element_url\":\"/\",\"elementClasses\":\"game-image-holder\",\"elementId\":\"\",\"elementText\":\"KM%20เล่นจริง%20Fish%20Prawn%20Crab%202\",\"dataanalyticsID\":\"null\"}":1075884,
    "{\"element_url\":\"/Slots\",\"elementClasses\":\"nuxt-link-exact-active%20nuxt-link-active\",\"elementId\":\"\",\"elementText\":\"สล็อต\",\"dataanalyticsID\":\"null\"}":1075886,
    "{\"element_url\":\"/\",\"elementClasses\":\"game-image-holder\",\"elementId\":\"\",\"elementText\":\"PP%20เล่นจริง%20หรือลองดูตัวอย่าง%20Gates%20of%20Olympus™\",\"dataanalyticsID\":\"null\"}":1075896,
    "{\"element_url\":\"/\",\"elementClasses\":\"\",\"elementId\":\"\",\"elementText\":\"ยอดเงินของคุณดูเหมือนจะเหลือน้อย\",\"dataanalyticsID\":\"null\"}":1075900,
    "{\"element_url\":\"/\",\"elementClasses\":\"v-icon%20icon%20icon-jw-fishgame%20theme--dark\",\"elementId\":\"\",\"elementText\":\"\",\"dataanalyticsID\":\"null\"}":1075949,
    "{\"element_url\":\"/\",\"elementClasses\":\"liveChatItem\",\"elementId\":\"\",\"elementText\":\"แชทสด\",\"dataanalyticsID\":\"null\"}":1075973,
    "{\"element_url\":\"/\",\"elementClasses\":\"v-text-field__slot\",\"elementId\":\"\",\"elementText\":\"เบอร์มือถือ\",\"dataanalyticsID\":\"null\"}":1075976,
    "{\"element_url\":\"/\",\"elementClasses\":\"game-image-holder\",\"elementId\":\"\",\"elementText\":\"CQ9%20เล่นจริง%20หรือลองดูตัวอย่าง%20JumpHigher\",\"dataanalyticsID\":\"null\"}":1076010,
    "{\"element_url\":\"/\",\"elementClasses\":\"v-icon%20mdi%20mdi-lock%20theme--dark\",\"elementId\":\"\",\"elementText\":\"\",\"dataanalyticsID\":\"null\"}":1076072,
    "{\"element_url\":\"/\",\"elementClasses\":\"v-icon%20v-icon--link%20mdi%20mdi-email%20theme--dark%20primary--text\",\"elementId\":\"\",\"elementText\":\"\",\"dataanalyticsID\":\"null\"}":1076112,
    "{\"element_url\":\"/\",\"elementClasses\":\"v-input__slot\",\"elementId\":\"\",\"elementText\":\"อีเมล\",\"dataanalyticsID\":\"null\"}":1076114,
    "{\"element_url\":\"/\",\"elementClasses\":\"errorList\",\"elementId\":\"\",\"elementText\":\"*%20คำขอ\",\"dataanalyticsID\":\"null\"}":1076115,
    "{\"element_url\":\"/\",\"elementClasses\":\"v-icon%20v-icon--link%20mdi%20mdi-email%20theme--dark\",\"elementId\":\"\",\"elementText\":\"\",\"dataanalyticsID\":\"null\"}":1076116,
    "{\"element_url\":\"/\",\"elementClasses\":\"_hj-21t0-__MinimizedWidgetMiddle__label\",\"elementId\":\"\",\"elementText\":\"Feedback\",\"dataanalyticsID\":\"null\"}":1076178,
    "{\"element_url\":\"/\",\"elementClasses\":\"label\",\"elementId\":\"\",\"elementText\":\"ข่าวสาร\",\"dataanalyticsID\":\"null\"}":1076215,
    "{\"element_url\":\"/en\",\"elementClasses\":\"\",\"elementId\":\"\",\"elementText\":\"Home\",\"dataanalyticsID\":\"null\"}":1076227,
    "{\"element_url\":\"/\",\"elementClasses\":\"game-info\",\"elementId\":\"\",\"elementText\":\"Magic%20Lamp\",\"dataanalyticsID\":\"null\"}":1076239,
    "{\"element_url\":\"/\",\"elementClasses\":\"loginModal-wrapper\",\"elementId\":\"\",\"elementText\":\"เข้าสู่ระบบ%20ชื่อผู้ใช้%20รหัสผ่าน%20check_box_outline_blank%20จดจำฉัน%20เข้าสู่ระบบ%20ยังไม่เป็นสมาชิก?%20สมัครสมาชิก%20ลืมรหัสผ่าน?\",\"dataanalyticsID\":\"null\"}":1076334,
    "{\"element_url\":\"/\",\"elementClasses\":\"v-text-field__slot\",\"elementId\":\"\",\"elementText\":\"อีเมล\",\"dataanalyticsID\":\"null\"}":1076339,
    "{\"element_url\":\"/\",\"elementClasses\":\"v-icon%20v-tabs__icon%20v-tabs__icon--next%20v-icon--link%20material-icons%20theme--dark\",\"elementId\":\"\",\"elementText\":\"chevron_right\",\"dataanalyticsID\":\"null\"}":1076353,
    "{\"element_url\":\"/\",\"elementClasses\":\"v-label%20theme--dark\",\"elementId\":\"\",\"elementText\":\"จดจำฉัน\",\"dataanalyticsID\":\"null\"}":1076408,
    "{\"element_url\":\"/\",\"elementClasses\":\"\",\"elementId\":\"\",\"elementText\":\"ยืนยัน\",\"dataanalyticsID\":\"null\"}":1076477,
    "{\"element_url\":\"/v2/SI/PromotionInfoLanguage3640\",\"elementClasses\":\"\",\"elementId\":\"\",\"elementText\":\"\",\"dataanalyticsID\":\"null\"}":1076501,
    "{\"element_url\":\"/\",\"elementClasses\":\"iconWrapper\",\"elementId\":\"\",\"elementText\":\"\",\"dataanalyticsID\":\"null\"}":1076522,
    "{\"element_url\":\"/\",\"elementClasses\":\"v-icon%20v-icon--link%20mdi%20mdi-account%20theme--dark\",\"elementId\":\"\",\"elementText\":\"\",\"dataanalyticsID\":\"null\"}":1076537,
    "{\"element_url\":\"/SignUp\",\"elementClasses\":\"signUp%20nuxt-link-exact-active%20nuxt-link-active\",\"elementId\":\"\",\"elementText\":\"สมัครสมาชิก\",\"dataanalyticsID\":\"null\"}":1076553,
    "{\"element_url\":\"/\",\"elementClasses\":\"v-tabs__item%20v-tabs__item--active\",\"elementId\":\"\",\"elementText\":\"เกมยิงปลา\",\"dataanalyticsID\":\"null\"}":1076570,
    "{\"element_url\":\"/\",\"elementClasses\":\"v-label%20theme--dark\",\"elementId\":\"\",\"elementText\":\"login.forgotPass.notify.sms\",\"dataanalyticsID\":\"null\"}":1076596,
    "{\"element_url\":\"/\",\"elementClasses\":\"form-group%20notifyWrap\",\"elementId\":\"\",\"elementText\":\"login.forgotPass.notify.p%20radio_button_unchecked%20login.forgotPass.notify.email%20radio_button_checked%20login.forgotPass.notify.sms\",\"dataanalyticsID\":\"null\"}":1076599,
    "{\"element_url\":\"/\",\"elementClasses\":\"jwbtn%20jwbtn-primary\",\"elementId\":\"\",\"elementText\":\"ยืนยัน\",\"dataanalyticsID\":\"null\"}":1076600,
    "{\"element_url\":\"/\",\"elementClasses\":\"help-text%20text-lg-right\",\"elementId\":\"\",\"elementText\":\"วิธีรับคะแนนสะสม?\",\"dataanalyticsID\":\"null\"}":1076666,
    "{\"element_url\":\"/\",\"elementClasses\":\"_hj-2OZKe__EmotionOption__expressionIcon\",\"elementId\":\"\",\"elementText\":\"\",\"dataanalyticsID\":\"null\"}":1076731,
    "{\"element_url\":\"/SignUp\",\"elementClasses\":\"nuxt-link-exact-active%20nuxt-link-active\",\"elementId\":\"\",\"elementText\":\"สมัครสมาชิก\",\"dataanalyticsID\":\"null\"}":1076741,
    "{\"element_url\":\"/\",\"elementClasses\":\"\",\"elementId\":\"\",\"elementText\":\"ผู้เล่นจะได้รับโบนัส%20200%20บาท%20จากโปรโมชั่นนี้%20และถอนได้สูงสุด%20-RAND-บาท\",\"dataanalyticsID\":\"null\"}":1076795,
    "{\"element_url\":\"/\",\"elementClasses\":\"_hj-2JN4b__ExpandedWidget__closeButton\",\"elementId\":\"\",\"elementText\":\"\",\"dataanalyticsID\":\"null\"}":1076824,
    "{\"element_url\":\"/v2/SI/PromotionInfoLanguage2240\",\"elementClasses\":\"\",\"elementId\":\"\",\"elementText\":\"\",\"dataanalyticsID\":\"null\"}":1076864,
    "{\"element_url\":\"/\",\"elementClasses\":\"v-icon%20closeBtn%20v-icon--link%20mdi%20mdi-close%20theme--dark\",\"elementId\":\"\",\"elementText\":\"\",\"dataanalyticsID\":\"null\"}":1076928,
    "{\"element_url\":\"/\",\"elementClasses\":\"loginModal-wrapper\",\"elementId\":\"\",\"elementText\":\"เข้าสู่ระบบ%20ชื่อผู้ใช้%20*%20จำเป็นต้อง%20รหัสผ่าน%20*%20จำเป็นต้อง%20check_box_outline_blank%20จดจำฉัน%20เข้าสู่ระบบ%20ยังไม่เป็นสมาชิก?%20สมัครสมาชิก%20ลืมรหัสผ่าน?\",\"dataanalyticsID\":\"null\"}":1076956,
    "{\"element_url\":\"/\",\"elementClasses\":\"game-image-holder\",\"elementId\":\"\",\"elementText\":\"PG%20เล่นจริง%20Ways%20of%20the%20Qilin\",\"dataanalyticsID\":\"null\"}":1076989,
    "{\"element_url\":\"/\",\"elementClasses\":\"_hj-2bByr__EmotionComment__textArea%20_hj-FAirH__styles__inputField\",\"elementId\":\"\",\"elementText\":\"\",\"dataanalyticsID\":\"null\"}":1077010,
    "{\"element_url\":\"/\",\"elementClasses\":\"_hj-KMOYv__EmailStep__input\",\"elementId\":\"email-address\",\"elementText\":\"\",\"dataanalyticsID\":\"null\"}":1077013,
    "{\"element_url\":\"/\",\"elementClasses\":\"v-icon%20backIcon%20mdi%20mdi-chevron-left%20theme--dark\",\"elementId\":\"\",\"elementText\":\"\",\"dataanalyticsID\":\"null\"}":1077106,
    "{\"element_url\":\"/promotions\",\"elementClasses\":\"\",\"elementId\":\"\",\"elementText\":\"\",\"dataanalyticsID\":\"null\"}":1077107,
    "{\"element_url\":\"/\",\"elementClasses\":\"resendPin\",\"elementId\":\"\",\"elementText\":\"ส่งรหัสอีกครั้ง%20(2)\",\"dataanalyticsID\":\"null\"}":1077113,
    "{\"element_url\":\"/\",\"elementClasses\":\"v-text-field__slot\",\"elementId\":\"\",\"elementText\":\"\",\"dataanalyticsID\":\"null\"}":1077114,
    "{\"element_url\":\"/\",\"elementClasses\":\"jwbtn%20jwbtn-primary%20sign-upbtn%20jw-text\",\"elementId\":\"\",\"elementText\":\"สมัครสมาชิก\",\"dataanalyticsID\":\"null\"}":1077118,
    "{\"element_url\":\"/\",\"elementClasses\":\"resendPin\",\"elementId\":\"\",\"elementText\":\"ส่งรหัสอีกครั้ง%20(1)\",\"dataanalyticsID\":\"null\"}":1077125,
    "{\"element_url\":\"/\",\"elementClasses\":\"loginModal-wrapper\",\"elementId\":\"\",\"elementText\":\"เข้าสู่ระบบ%20ชื่อผู้ใช้%20รหัสผ่าน%20*ชื่อผู้ใช้หรือรหัสผ่านไม่ถูกต้อง%20check_box_outline_blank%20จดจำฉัน%20เข้าสู่ระบบ%20ยังไม่เป็นสมาชิก?%20สมัครสมาชิก%20ลืมรหัสผ่าน?\",\"dataanalyticsID\":\"null\"}":1077134,
    "{\"element_url\":\"/\",\"elementClasses\":\"v-input%20rememberMe%20v-input--selection-controls%20v-input--checkbox%20v-input--is-label-active%20v-input--is-dirty%20theme--dark\",\"elementId\":\"\",\"elementText\":\"check_box%20จดจำฉัน\",\"dataanalyticsID\":\"null\"}":1077192,
    "{\"element_url\":\"/\",\"elementClasses\":\"close-icon-wrapper\",\"elementId\":\"\",\"elementText\":\"\",\"dataanalyticsID\":\"null\"}":1077231,
    "{\"element_url\":\"/\",\"elementClasses\":\"\",\"elementId\":\"\",\"elementText\":\"SEXY%20Friday\",\"dataanalyticsID\":\"null\"}":1077276,
    "{\"element_url\":\"/service/image/13bf5e90-5917-11ea-a29e-e94db9e75abe\",\"elementClasses\":\"\",\"elementId\":\"\",\"elementText\":\"\",\"dataanalyticsID\":\"null\"}":1077299,
    "{\"element_url\":\"/\",\"elementClasses\":\"v-input--selection-controls__ripple%20primary--text\",\"elementId\":\"\",\"elementText\":\"\",\"dataanalyticsID\":\"null\"}":1077399,
    "{\"element_url\":\"/\",\"elementClasses\":\"jwbtn%20viewMoreButton\",\"elementId\":\"\",\"elementText\":\"Load%20More%20Games\",\"dataanalyticsID\":\"null\"}":1077417,
    "{\"element_url\":\"/\",\"elementClasses\":\"promotionContainer%20page-margin-bottom\",\"elementId\":\"promoScrollIndex\",\"elementText\":\"กำลังโหลดรายการโปรโมชั่น%20...\",\"dataanalyticsID\":\"null\"}":1077422,
    "{\"element_url\":\"/\",\"elementClasses\":\"v-dialog%20lowBalContainer%20v-dialog--active%20v-dialog--persistent%20v-dialog--scrollable\",\"elementId\":\"\",\"elementText\":\"ต้องการที่จะเติมเงินก่อนที่จะเล่นหรือไม่?%20ดำเนินการต่อเพื่อเล่นเกม%20-or-%20ฝากเงิน\",\"dataanalyticsID\":\"null\"}":1077626,
    "{\"element_url\":\"/\",\"elementClasses\":\"v-icon%20userIcon%20mdi%20mdi-menu%20theme--dark\",\"elementId\":\"\",\"elementText\":\"\",\"dataanalyticsID\":\"null\"}":1077656,
    "{\"element_url\":\"/\",\"elementClasses\":\"link\",\"elementId\":\"\",\"elementText\":\"ฝ่ายบริการลูกค้า\",\"dataanalyticsID\":\"null\"}":1077740,
    "{\"element_url\":\"/\",\"elementClasses\":\"\",\"elementId\":\"\",\"elementText\":\"ในการเริ่มต้นเพียงลงทะเบียนบัญชีทำการฝากเงินครั้งแรกของคุณและรับคะแนนสะสม%20-RAND-%20คะแนนภายใน%2024%20ชั่วโมง%20ระดับชั้นของผู้เล่นที่มีอยู่ขึ้นอยู่กับคะแนนรางวัลปัจจุบันของพวกเขา%20สำหรับข้อมูลเพิ่มเติมกรุณาติดต่อฝ่ายบริการลูกค้าและเรียนรู้เพิ่มเติมเกี่ยวกับระดับชั้นและจุดบำรุงรักษา\",\"dataanalyticsID\":\"null\"}":1077753,
    "{\"element_url\":\"/\",\"elementClasses\":\"v-text-field__slot\",\"elementId\":\"\",\"elementText\":\"รหัสผ่าน\",\"dataanalyticsID\":\"null\"}":1077779,
    "{\"element_url\":\"/\",\"elementClasses\":\"icon-close\",\"elementId\":\"\",\"elementText\":\"\",\"dataanalyticsID\":\"null\"}":1077789,
    "{\"element_url\":\"/\",\"elementClasses\":\"v-input__slot\",\"elementId\":\"\",\"elementText\":\"\",\"dataanalyticsID\":\"null\"}":1077896,
    "{\"element_url\":\"/\",\"elementClasses\":\"game-image-holder\",\"elementId\":\"\",\"elementText\":\"JDB%20เล่นจริง%20Triple%20King%20Kong\",\"dataanalyticsID\":\"null\"}":1077944,
    "{\"element_url\":\"/\",\"elementClasses\":\"v-icon%20mdi%20mdi-email%20theme--dark\",\"elementId\":\"\",\"elementText\":\"\",\"dataanalyticsID\":\"null\"}":1077966,
    "{\"element_url\":\"/\",\"elementClasses\":\"v-icon%20mdi%20mdi-account%20theme--dark\",\"elementId\":\"\",\"elementText\":\"\",\"dataanalyticsID\":\"null\"}":1077979,
    "{\"element_url\":\"/\",\"elementClasses\":\"\",\"elementId\":\"\",\"elementText\":\"คาสิโนสด\",\"dataanalyticsID\":\"null\"}":1078020,
    "{\"element_url\":\"/\",\"elementClasses\":\"v-icon%20icon%20icon-jw-club%20theme--dark\",\"elementId\":\"\",\"elementText\":\"\",\"dataanalyticsID\":\"null\"}":1078123,
    "{\"element_url\":\"/v2/SI/PromotionInfoLanguage4440\",\"elementClasses\":\"\",\"elementId\":\"\",\"elementText\":\"\",\"dataanalyticsID\":\"null\"}":1078130,
    "{\"element_url\":\"/\",\"elementClasses\":\"game-info\",\"elementId\":\"\",\"elementText\":\"Roma\",\"dataanalyticsID\":\"null\"}":1078151,
    "{\"element_url\":\"/\",\"elementClasses\":\"image\",\"elementId\":\"\",\"elementText\":\"\",\"dataanalyticsID\":\"null\"}":1078190,
    "{\"element_url\":\"/\",\"elementClasses\":\"ticket-btn\",\"elementId\":\"\",\"elementText\":\"Use%20Now\",\"dataanalyticsID\":\"null\"}":1078191,
    "{\"element_url\":\"/\",\"elementClasses\":\"ticket-btn\",\"elementId\":\"\",\"elementText\":\"Using\",\"dataanalyticsID\":\"null\"}":1078192,
    "{\"element_url\":\"/\",\"elementClasses\":\"v-input__slot\",\"elementId\":\"\",\"elementText\":\"เบอร์มือถือ\",\"dataanalyticsID\":\"null\"}":1078362,
    "{\"element_url\":\"/\",\"elementClasses\":\"right-section\",\"elementId\":\"\",\"elementText\":\"เข้าสู่ระบบ%20สมัครสมาชิก%20TH\",\"dataanalyticsID\":\"null\"}":1078452,
    "{\"element_url\":\"/\",\"elementClasses\":\"errorList\",\"elementId\":\"\",\"elementText\":\"*%20จำเป็นต้อง\",\"dataanalyticsID\":\"null\"}":1078483,
    "{\"element_url\":\"/v2/SI/PromotionInfoLanguage840\",\"elementClasses\":\"\",\"elementId\":\"\",\"elementText\":\"\",\"dataanalyticsID\":\"null\"}":1078487,
    "{\"element_url\":\"/\",\"elementClasses\":\"\",\"elementId\":\"\",\"elementText\":\"ยังไม่เป็นสมาชิก?%20สมัครสมาชิก\",\"dataanalyticsID\":\"null\"}":1078519,
    "{\"element_url\":\"/\",\"elementClasses\":\"v-label%20theme--dark\",\"elementId\":\"\",\"elementText\":\"login.forgotPass.notify.email\",\"dataanalyticsID\":\"null\"}":1078651,
    "{\"element_url\":\"/\",\"elementClasses\":\"header-3\",\"elementId\":\"\",\"elementText\":\"กรุณากรอกแบบฟอร์มสมัรสมาชิกด้านล่าง\",\"dataanalyticsID\":\"null\"}":1078726,
    "{\"element_url\":\"/\",\"elementClasses\":\"v-input__slot\",\"elementId\":\"\",\"elementText\":\"รหัสรักษาความปลอดภัย\",\"dataanalyticsID\":\"null\"}":1078728,
    "{\"element_url\":\"/\",\"elementClasses\":\"captcha-wrapper\",\"elementId\":\"\",\"elementText\":\"รหัสรักษาความปลอดภัย\",\"dataanalyticsID\":\"null\"}":1078729,
    "{\"element_url\":\"/\",\"elementClasses\":\"tab\",\"elementId\":\"\",\"elementText\":\"ข่าวสาร\",\"dataanalyticsID\":\"null\"}":1078816,
    "{\"element_url\":\"/Other-Games\",\"elementClasses\":\"nuxt-link-exact-active%20nuxt-link-active\",\"elementId\":\"\",\"elementText\":\"อื่นๆ\",\"dataanalyticsID\":\"null\"}":1078917,
    "{\"element_url\":\"/\",\"elementClasses\":\"hide-mobile\",\"elementId\":\"\",\"elementText\":\"VIP\",\"dataanalyticsID\":\"null\"}":1078985,
    "{\"element_url\":\"/\",\"elementClasses\":\"promotionModalTitle\",\"elementId\":\"\",\"elementText\":\"วงล้อนำโชค\",\"dataanalyticsID\":\"null\"}":1079012,
    "{\"element_url\":\"/\",\"elementClasses\":\"jwbtn%20jwbtn-blue%20lowBalBtn\",\"elementId\":\"\",\"elementText\":\"ดำเนินการต่อเพื่อเล่นเกม\",\"dataanalyticsID\":\"null\"}":1079064,
    "{\"element_url\":\"/\",\"elementClasses\":\"game-image-holder\",\"elementId\":\"\",\"elementText\":\"JILI%20เล่นจริง%20Charge%20Buffalo\",\"dataanalyticsID\":\"null\"}":1079213,
    "{\"element_url\":\"/\",\"elementClasses\":\"gameSearch\",\"elementId\":\"searchQuery\",\"elementText\":\"\",\"dataanalyticsID\":\"null\"}":1079259,
    "{\"element_url\":\"/\",\"elementClasses\":\"game-image-holder\",\"elementId\":\"\",\"elementText\":\"PP%20เล่นจริง%20หรือลองดูตัวอย่าง%20Magician-singleQuotePLH-s%20Secrets™️\",\"dataanalyticsID\":\"null\"}":1079310,
    "{\"element_url\":\"/\",\"elementClasses\":\"profileWrapper\",\"elementId\":\"\",\"elementText\":\"Waree1230%20Elite\",\"dataanalyticsID\":\"null\"}":1079437,
    "{\"element_url\":\"/\",\"elementClasses\":\"\",\"elementId\":\"\",\"elementText\":\"RomaX\",\"dataanalyticsID\":\"null\"}":1079468,
    "{\"element_url\":\"/\",\"elementClasses\":\"game-image-holder\",\"elementId\":\"\",\"elementText\":\"ISB%20เล่นจริง%20หรือลองดูตัวอย่าง%20Prosperity%20Ox\",\"dataanalyticsID\":\"null\"}":1079563,
    "{\"element_url\":\"/\",\"elementClasses\":\"\",\"elementId\":\"\",\"elementText\":\"0%20-RAND-\",\"dataanalyticsID\":\"null\"}":1079578,
    "{\"element_url\":\"/\",\"elementClasses\":\"content-wrapper\",\"elementId\":\"\",\"elementText\":\"สร้างบัญชีบน%20Siam99%20เพื่อเล่นเกมออนไลน์ที่น่าตื่นเต้นทั้งหมด%20ไม่มีข้อจำกัด%20ฟรี%20กรุณากรอกแบบฟอร์มสมัรสมาชิกด้านล่าง%20ชื่อผู้ใช้%20รหัสผ่าน%20ยืนยันรหัสผ่าน%20ชื่อ-นามสกุล%20อีเมล%20เบอร์มือถือ%20รหัสรักษาความปลอดภัย%20สมัครสมาชิก\",\"dataanalyticsID\":\"null\"}":1079618,
    "{\"element_url\":\"/\",\"elementClasses\":\"vdatetime-time-picker__item\",\"elementId\":\"\",\"elementText\":\"\",\"dataanalyticsID\":\"null\"}":1079634,
    "{\"element_url\":\"/\",\"elementClasses\":\"labelText\",\"elementId\":\"\",\"elementText\":\"เปลี่ยนรหัสผ่าน\",\"dataanalyticsID\":\"null\"}":1079684,
    "{\"element_url\":\"/\",\"elementClasses\":\"lowBalanceHeader\",\"elementId\":\"\",\"elementText\":\"ต้องการที่จะเติมเงินก่อนที่จะเล่นหรือไม่?\",\"dataanalyticsID\":\"null\"}":1079911,
    "{\"element_url\":\"/\",\"elementClasses\":\"v-tabs__item%20v-tabs__item--active\",\"elementId\":\"\",\"elementText\":\"ทั้งหมด\",\"dataanalyticsID\":\"null\"}":1079925,
    "{\"element_url\":\"/\",\"elementClasses\":\"v-icon%20mdi%20mdi-chevron-down%20theme--dark\",\"elementId\":\"\",\"elementText\":\"\",\"dataanalyticsID\":\"null\"}":1079935,
    "{\"element_url\":\"/\",\"elementClasses\":\"downloadNotificationContentWrapper%20center\",\"elementId\":\"\",\"elementText\":\"\",\"dataanalyticsID\":\"null\"}":1079940,
    "{\"element_url\":\"/\",\"elementClasses\":\"v-tabs__item\",\"elementId\":\"\",\"elementText\":\"สล็อต\",\"dataanalyticsID\":\"null\"}":1079955,
    "{\"element_url\":\"/\",\"elementClasses\":\"v-tabs__item%20v-tabs__item--active\",\"elementId\":\"\",\"elementText\":\"สล็อต\",\"dataanalyticsID\":\"null\"}":1079956,
    "{\"element_url\":\"/\",\"elementClasses\":\"v-icon%20mdi%20mdi-cached%20theme--dark\",\"elementId\":\"\",\"elementText\":\"\",\"dataanalyticsID\":\"null\"}":1080049,
    "{\"element_url\":\"/\",\"elementClasses\":\"game-name\",\"elementId\":\"\",\"elementText\":\"Roma\",\"dataanalyticsID\":\"null\"}":1080057,
    "{\"element_url\":\"/\",\"elementClasses\":\"\",\"elementId\":\"rememberMe\",\"elementText\":\"\",\"dataanalyticsID\":\"null\"}":1080277,
    "{\"element_url\":\"/\",\"elementClasses\":\"container%20gameListWrapper%20grid-list-cs\",\"elementId\":\"\",\"elementText\":\"กำลังโหลดรายชื่อเกม...\",\"dataanalyticsID\":\"null\"}":1080290,
    "{\"element_url\":\"/v2/SI/PromotionInfoLanguage640\",\"elementClasses\":\"\",\"elementId\":\"\",\"elementText\":\"\",\"dataanalyticsID\":\"null\"}":1080318,
    "{\"element_url\":\"/v2/SI/PromotionInfoLanguage740\",\"elementClasses\":\"\",\"elementId\":\"\",\"elementText\":\"\",\"dataanalyticsID\":\"null\"}":1080740,
    "{\"element_url\":\"/\",\"elementClasses\":\"\",\"elementId\":\"\",\"elementText\":\"Mahjong%20Ways%202\",\"dataanalyticsID\":\"null\"}":1080962,
    "{\"element_url\":\"/\",\"elementClasses\":\"game-image-holder\",\"elementId\":\"\",\"elementText\":\"JILI%20เล่นจริง%20RomaX\",\"dataanalyticsID\":\"null\"}":1080980,
    "{\"element_url\":\"/\",\"elementClasses\":\"v-icon%20icon%20icon-jw-casinolive%20theme--dark\",\"elementId\":\"\",\"elementText\":\"\",\"dataanalyticsID\":\"null\"}":1081039,
    "{\"element_url\":\"/\",\"elementClasses\":\"form-content\",\"elementId\":\"\",\"elementText\":\"ชื่อผู้ใช้%20รหัสผ่าน%20ยืนยันรหัสผ่าน%20ชื่อ-นามสกุล%20อีเมล%20เบอร์มือถือ%20รหัสรักษาความปลอดภัย%20*%20คำขอ%20*%20Captcha%20ไม่ถูกต้อง%20สมัครสมาชิก\",\"dataanalyticsID\":\"null\"}":1081135,
    "{\"element_url\":\"/\",\"elementClasses\":\"labelText\",\"elementId\":\"\",\"elementText\":\"วงล้อนำโชค\",\"dataanalyticsID\":\"null\"}":1081158,
    "{\"element_url\":\"/\",\"elementClasses\":\"v-icon%20mdi%20mdi-logout%20theme--dark\",\"elementId\":\"\",\"elementText\":\"\",\"dataanalyticsID\":\"null\"}":1081216,
    "{\"element_url\":\"/\",\"elementClasses\":\"\",\"elementId\":\"\",\"elementText\":\"แชทสด\",\"dataanalyticsID\":\"null\"}":1081237,
    "{\"element_url\":\"/\",\"elementClasses\":\"vdatetime-popup__actions__button%20vdatetime-popup__actions__button--confirm\",\"elementId\":\"\",\"elementText\":\"\",\"dataanalyticsID\":\"null\"}":1081384,
    "{\"element_url\":\"/\",\"elementClasses\":\"\",\"elementId\":\"\",\"elementText\":\"คัดลอกลิงค์แล้ว\",\"dataanalyticsID\":\"null\"}":1081501,
    "{\"element_url\":\"/\",\"elementClasses\":\"\",\"elementId\":\"\",\"elementText\":\"มือใหม่\",\"dataanalyticsID\":\"null\"}":1081531,
    "{\"element_url\":\"/\",\"elementClasses\":\"v-tabs__item\",\"elementId\":\"\",\"elementText\":\"เงินคืน\",\"dataanalyticsID\":\"null\"}":1081536,
    "{\"element_url\":\"/\",\"elementClasses\":\"v-tabs__item%20v-tabs__item--active\",\"elementId\":\"\",\"elementText\":\"เงินคืน\",\"dataanalyticsID\":\"null\"}":1081537,
    "{\"element_url\":\"/\",\"elementClasses\":\"game-image-holder\",\"elementId\":\"\",\"elementText\":\"PG%20เล่นจริง%20Ganesha%20Fortune\",\"dataanalyticsID\":\"null\"}":1081553,
    "{\"element_url\":\"/\",\"elementClasses\":\"spinWinInfo\",\"elementId\":\"\",\"elementText\":\"ยินดีด้วย!%20คุณมีฟรีสปิน%20หมุนเดี๋ยวนี้\",\"dataanalyticsID\":\"null\"}":1081560,
    "{\"element_url\":\"/\",\"elementClasses\":\"\",\"elementId\":\"\",\"elementText\":\"login.forgotPass.notify.p\",\"dataanalyticsID\":\"null\"}":1081719,
    "{\"element_url\":\"/\",\"elementClasses\":\"\",\"elementId\":\"\",\"elementText\":\"Load%20More%20Games\",\"dataanalyticsID\":\"null\"}":1081785,
    "{\"element_url\":\"/\",\"elementClasses\":\"copy-text\",\"elementId\":\"\",\"elementText\":\"คัดลอกลิงค์แล้ว\",\"dataanalyticsID\":\"null\"}":1081884,
    "{\"element_url\":\"/\",\"elementClasses\":\"game-image-holder\",\"elementId\":\"\",\"elementText\":\"JILI%20เล่นจริง%20FaFaFa\",\"dataanalyticsID\":\"null\"}":1082508,
    "{\"element_url\":\"/service/image/5e4eaf60-a357-11ec-959e-4f672dbb0d08\",\"elementClasses\":\"\",\"elementId\":\"\",\"elementText\":\"\",\"dataanalyticsID\":\"null\"}":1082538,
    "{\"element_url\":\"/en/Sports\",\"elementClasses\":\"\",\"elementId\":\"\",\"elementText\":\"Sports\",\"dataanalyticsID\":\"null\"}":1082545,
    "{\"element_url\":\"/\",\"elementClasses\":\"jwbtn%20jwbtn-green%20lowBalBtn\",\"elementId\":\"\",\"elementText\":\"ฝากเงิน\",\"dataanalyticsID\":\"null\"}":1082633,
    "{\"element_url\":\"/\",\"elementClasses\":\"resendPin%20disabled\",\"elementId\":\"\",\"elementText\":\"ส่งรหัสอีกครั้ง%20(0)\",\"dataanalyticsID\":\"null\"}":1082681,
    "{\"element_url\":\"/\",\"elementClasses\":\"v-select__selections\",\"elementId\":\"\",\"elementText\":\"\",\"dataanalyticsID\":\"null\"}":1082853,
    "{\"element_url\":\"/\",\"elementClasses\":\"game-image-holder\",\"elementId\":\"\",\"elementText\":\"YGG%20เล่นจริง%20Zeus%20Vs%20Thor\",\"dataanalyticsID\":\"null\"}":1082908,
    "{\"element_url\":\"/\",\"elementClasses\":\"game-image-holder\",\"elementId\":\"\",\"elementText\":\"RSG%20เล่นจริง%205%20Dragons\",\"dataanalyticsID\":\"null\"}":1083097,
    "{\"element_url\":\"/v2/SI/PictureLanguage.238.4\",\"elementClasses\":\"swiper-lazy%20swiper-lazy-loaded\",\"elementId\":\"\",\"elementText\":\"\",\"dataanalyticsID\":\"null\"}":1083177,
    "{\"element_url\":\"/service/image/e6075260-c41c-11eb-8301-f9030f6918e4\",\"elementClasses\":\"\",\"elementId\":\"\",\"elementText\":\"\",\"dataanalyticsID\":\"null\"}":1083326,
    "{\"element_url\":\"/en/quick\",\"elementClasses\":\"\",\"elementId\":\"\",\"elementText\":\"More\",\"dataanalyticsID\":\"null\"}":1083414,
    "{\"element_url\":\"/\",\"elementClasses\":\"form-group%20captcha-wrapper\",\"elementId\":\"\",\"elementText\":\"รหัสผ้องกัน\",\"dataanalyticsID\":\"null\"}":1083578,
    "{\"element_url\":\"/\",\"elementClasses\":\"\",\"elementId\":\"\",\"elementText\":\"Requirements\",\"dataanalyticsID\":\"null\"}":1083675,
    "{\"element_url\":\"/\",\"elementClasses\":\"\",\"elementId\":\"\",\"elementText\":\"Benefits\",\"dataanalyticsID\":\"null\"}":1083679,
    "{\"element_url\":\"/\",\"elementClasses\":\"\",\"elementId\":\"\",\"elementText\":\"Caishen%20Wins\",\"dataanalyticsID\":\"null\"}":1083815,
    "{\"element_url\":\"/pn/sw/prod/platform/icon/v2/YGG/icon_1629873629547.png\",\"elementClasses\":\"platformIcon\",\"elementId\":\"\",\"elementText\":\"\",\"dataanalyticsID\":\"null\"}":1083821,
    "{\"element_url\":\"/pn/sw/prod/platform/icon/v2/ISB/1629871970104.png\",\"elementClasses\":\"platformIcon\",\"elementId\":\"\",\"elementText\":\"\",\"dataanalyticsID\":\"null\"}":1083823,
    "{\"element_url\":\"/en/promotions\",\"elementClasses\":\"\",\"elementId\":\"\",\"elementText\":\"Promotions\",\"dataanalyticsID\":\"null\"}":1084041,
    "{\"element_url\":\"/\",\"elementClasses\":\"game-name\",\"elementId\":\"\",\"elementText\":\"Lucky%20Neko\",\"dataanalyticsID\":\"null\"}":1084064,
    "{\"element_url\":\"/\",\"elementClasses\":\"\",\"elementId\":\"\",\"elementText\":\"Golden%20Empire\",\"dataanalyticsID\":\"null\"}":1084084,
    "{\"element_url\":\"/\",\"elementClasses\":\"platformName\",\"elementId\":\"\",\"elementText\":\"All\",\"dataanalyticsID\":\"null\"}":1084186,
    "{\"element_url\":\"/\",\"elementClasses\":\"jwbtn%20jwbtn-green%20redirectBtn\",\"elementId\":\"\",\"elementText\":\"หมุนเดี๋ยวนี้\",\"dataanalyticsID\":\"null\"}":1084218,
    "{\"element_url\":\"/\",\"elementClasses\":\"gameimg\",\"elementId\":\"\",\"elementText\":\"\",\"dataanalyticsID\":\"null\"}":1084291,
    "{\"element_url\":\"/\",\"elementClasses\":\"game-image-holder\",\"elementId\":\"\",\"elementText\":\"JDB%20เล่นจริง%20หรือลองดูตัวอย่าง%20Mjolnir\",\"dataanalyticsID\":\"null\"}":1084549,
    "{\"element_url\":\"/\",\"elementClasses\":\"game-image-holder\",\"elementId\":\"\",\"elementText\":\"PS%20เล่นจริง%20หรือลองดูตัวอย่าง%20Super%20Powerful\",\"dataanalyticsID\":\"null\"}":1084683,
    "{\"element_url\":\"/99Club\",\"elementClasses\":\"\",\"elementId\":\"\",\"elementText\":\"VIP\",\"dataanalyticsID\":\"null\"}":1084815,
    "{\"element_url\":\"/\",\"elementClasses\":\"\",\"elementId\":\"\",\"elementText\":\"chevron_right\",\"dataanalyticsID\":\"null\"}":1084898,
    "{\"element_url\":\"/\",\"elementClasses\":\"\",\"elementId\":\"\",\"elementText\":\"เข้าร่วมโปรโมชั่น\",\"dataanalyticsID\":\"null\"}":1084902,
    "{\"element_url\":\"/\",\"elementClasses\":\"game-image-holder\",\"elementId\":\"\",\"elementText\":\"SG%20เล่นจริง%20หรือลองดูตัวอย่าง%20Fishing%20War\",\"dataanalyticsID\":\"null\"}":1085445,
    "{\"element_url\":\"/\",\"elementClasses\":\"game-name\",\"elementId\":\"\",\"elementText\":\"Mahjong%20Ways\",\"dataanalyticsID\":\"null\"}":1085495,
    "{\"element_url\":\"/\",\"elementClasses\":\"resendPin%20disabled%20disabled%20requesting\",\"elementId\":\"\",\"elementText\":\"ส่งรหัสอีกครั้ง%20(30)\",\"dataanalyticsID\":\"null\"}":1085570,
    "{\"element_url\":\"/\",\"elementClasses\":\"_hj-cp7UI__HotjarBranding__hotjarBranding\",\"elementId\":\"\",\"elementText\":\"Not%20using%20Hotjar%20yet?\",\"dataanalyticsID\":\"null\"}":1085831,
    "{\"element_url\":\"/\",\"elementClasses\":\"v-input__slot\",\"elementId\":\"\",\"elementText\":\"check_box_outline_blank%20จดจำฉัน\",\"dataanalyticsID\":\"null\"}":1085886,
    "{\"element_url\":\"/\",\"elementClasses\":\"v-icon%20mdi%20mdi-earth%20theme--dark\",\"elementId\":\"\",\"elementText\":\"\",\"dataanalyticsID\":\"null\"}":1085989,
    "{\"element_url\":\"/\",\"elementClasses\":\"game-image-holder\",\"elementId\":\"\",\"elementText\":\"JDB%20เล่นจริง%20หรือลองดูตัวอย่าง%20SuperNuibi\",\"dataanalyticsID\":\"null\"}":1086006,
    "{\"element_url\":\"/\",\"elementClasses\":\"game-image-holder\",\"elementId\":\"\",\"elementText\":\"GMT%20เล่นจริง%20หรือลองดูตัวอย่าง%20Abduction\",\"dataanalyticsID\":\"null\"}":1086012,
    "{\"element_url\":\"/pn/sw/prod/platform/icon/v2/JDB/1629871848311.png\",\"elementClasses\":\"platformIcon\",\"elementId\":\"\",\"elementText\":\"\",\"dataanalyticsID\":\"null\"}":1086015,
    "{\"element_url\":\"/\",\"elementClasses\":\"v-text-field__slot\",\"elementId\":\"\",\"elementText\":\"ชื่อ-นามสกุล\",\"dataanalyticsID\":\"null\"}":1086035,
    "{\"element_url\":\"/\",\"elementClasses\":\"image-bg\",\"elementId\":\"\",\"elementText\":\"\",\"dataanalyticsID\":\"null\"}":1086444,
    "{\"element_url\":\"/\",\"elementClasses\":\"game-image-holder\",\"elementId\":\"\",\"elementText\":\"JILI%20เล่นจริง%20Golden%20Empire\",\"dataanalyticsID\":\"null\"}":1086515,
    "{\"element_url\":\"/\",\"elementClasses\":\"v-tabs__item\",\"elementId\":\"\",\"elementText\":\"ทั้งหมด\",\"dataanalyticsID\":\"null\"}":1086614,
    "{\"element_url\":\"/\",\"elementClasses\":\"v-icon%20mdi%20mdi-account-multiple-plus%20theme--dark\",\"elementId\":\"\",\"elementText\":\"\",\"dataanalyticsID\":\"null\"}":1086798,
    "{\"element_url\":\"/\",\"elementClasses\":\"form-content\",\"elementId\":\"\",\"elementText\":\"ชื่อผู้ใช้%20*%20ชื่อผู้ใช้ไม่ถูกต้อง%20รหัสผ่าน%20ยืนยันรหัสผ่าน%20ชื่อ-นามสกุล%20อีเมล%20เบอร์มือถือ%20รหัสรักษาความปลอดภัย%20สมัครสมาชิก\",\"dataanalyticsID\":\"null\"}":1087222,
    "{\"element_url\":\"/v2/SI/PictureLanguage.268.4\",\"elementClasses\":\"swiper-lazy%20swiper-lazy-loaded\",\"elementId\":\"\",\"elementText\":\"\",\"dataanalyticsID\":\"null\"}":1087399,
    "{\"element_url\":\"/\",\"elementClasses\":\"nuxt-link-active\",\"elementId\":\"\",\"elementText\":\"ออกจากระบบ\",\"dataanalyticsID\":\"null\"}":1088435,
    "{\"element_url\":\"/\",\"elementClasses\":\"imgWrapper%20align-grid-item-center\",\"elementId\":\"\",\"elementText\":\"ชนะสปิน\",\"dataanalyticsID\":\"null\"}":1088446,
    "{\"element_url\":\"/\",\"elementClasses\":\"form-group%20notifyWrap\",\"elementId\":\"\",\"elementText\":\"login.forgotPass.notify.p%20radio_button_checked%20login.forgotPass.notify.email%20radio_button_unchecked%20login.forgotPass.notify.sms\",\"dataanalyticsID\":\"null\"}":1088483,
    "{\"element_url\":\"/\",\"elementClasses\":\"game-image-holder\",\"elementId\":\"\",\"elementText\":\"PG%20เล่นจริง%20Wild%20Bandito\",\"dataanalyticsID\":\"null\"}":1088555,
    "{\"element_url\":\"/\",\"elementClasses\":\"\",\"elementId\":\"\",\"elementText\":\"กรุณาใส่หมายเลขที่คุณได้รับ\",\"dataanalyticsID\":\"null\"}":1088630,
    "{\"element_url\":\"/\",\"elementClasses\":\"spinNav\",\"elementId\":\"\",\"elementText\":\"วงล้อนำโชค\",\"dataanalyticsID\":\"null\"}":1088709,
    "{\"element_url\":\"/\",\"elementClasses\":\"game-image-holder\",\"elementId\":\"\",\"elementText\":\"PG%20เล่นจริง%20Treasures%20of%20Aztec\",\"dataanalyticsID\":\"null\"}":1089002,
    "{\"element_url\":\"/\",\"elementClasses\":\"promotionModalTitle\",\"elementId\":\"\",\"elementText\":\"Sexy%20Friday\",\"dataanalyticsID\":\"null\"}":1089204,
    "{\"element_url\":\"/\",\"elementClasses\":\"tier\",\"elementId\":\"\",\"elementText\":\"Elite\",\"dataanalyticsID\":\"null\"}":1089445,
    "{\"element_url\":\"/\",\"elementClasses\":\"game-image-holder\",\"elementId\":\"\",\"elementText\":\"RSG%20เล่นจริง%20Roma\",\"dataanalyticsID\":\"null\"}":1089926,
    "{\"element_url\":\"/\",\"elementClasses\":\"codeWrapper\",\"elementId\":\"\",\"elementText\":\"กรุณาใส่หมายเลขที่คุณได้รับ%20ยืนยันความถูกต้อง\",\"dataanalyticsID\":\"null\"}":1089967,
    "{\"element_url\":\"/pn/sw/prod/platform/icon/v2/NT/1629872233173.png\",\"elementClasses\":\"platformIcon\",\"elementId\":\"\",\"elementText\":\"\",\"dataanalyticsID\":\"null\"}":1090016,
    "{\"element_url\":\"/\",\"elementClasses\":\"forgotPageTitle\",\"elementId\":\"\",\"elementText\":\"ลืมรหัสผ่าน\",\"dataanalyticsID\":\"null\"}":1090084,
    "{\"element_url\":\"/\",\"elementClasses\":\"\",\"elementId\":\"\",\"elementText\":\"ค้นหา\",\"dataanalyticsID\":\"null\"}":1090151,
    "{\"element_url\":\"/\",\"elementClasses\":\"promotionContainer%20page-margin-bottom\",\"elementId\":\"promoScrollIndex\",\"elementText\":\"ทั้งหมด%20ฝาก%20ฟรีเครดิต%20กีฬา%20คาสิโนสด%20โบนัสต้อนรับ%20เงินคืน%20เหตุการณ์%20สล็อต%20เกมยิงปลา%20โชคดี%20วันอาทิตย์%20โบนัสแนะนำไม่%20จำกัด%20เงินคืน%20-RAND-%%20สำหรับ%20สล็อต%20และยิงปลา%20โบนัสเงินฝากรายวัน%205%%20โปรใหม่ให้โชค%20150%%20สมัครสมาชิกใหม่รับสปินฟรี%205ครั้ง%20โบนัสเงินฝากรายวัน%2050%%20Sexy%20Friday%20โบนัสต้อนรับ%20100%%20สล็อต%20โบนัสต้อนรับ%20100%%20ที่เกมยิงปลา%20โบนัสเติมเงินรายวัน%2020%%20เกมตกปลา%20ฝาก%20100%20รับฟรี%20200%20เฉพาะค่ายเกม%20JILI%20ฝาก%2050%20รับฟรี%20300%20วงล้อนำโชค%20คืนเงินกีฬา%20โบนัสวันเกิด%20คืนยอดเสียรายสัปดาห์%202X%20คะแนนสะสม\",\"dataanalyticsID\":\"null\"}":1091069,
    "{\"element_url\":\"/\",\"elementClasses\":\"v-tabs__item\",\"elementId\":\"\",\"elementText\":\"โบนัสต้อนรับ\",\"dataanalyticsID\":\"null\"}":1091191,
    "{\"element_url\":\"/\",\"elementClasses\":\"v-tabs__item%20v-tabs__item--active\",\"elementId\":\"\",\"elementText\":\"โบนัสต้อนรับ\",\"dataanalyticsID\":\"null\"}":1091192,
    "{\"element_url\":\"/\",\"elementClasses\":\"form-content\",\"elementId\":\"\",\"elementText\":\"ชื่อผู้ใช้%20รหัสผ่าน%20ยืนยันรหัสผ่าน%20ชื่อ-นามสกุล%20อีเมล%20เบอร์มือถือ%20รหัสรักษาความปลอดภัย\",\"dataanalyticsID\":\"null\"}":1091632,
    "{\"element_url\":\"/\",\"elementClasses\":\"forgotModal-wrapper\",\"elementId\":\"\",\"elementText\":\"ลืมรหัสผ่าน%20ชื่อผู้ใช้%20login.forgotPass.notify.p%20radio_button_unchecked%20login.forgotPass.notify.email%20radio_button_checked%20login.forgotPass.notify.sms%20login.forgotPass.phoneNumber%20*%20จำเป็นต้อง%20รหัสผ้องกัน%20ยืนยัน\",\"dataanalyticsID\":\"null\"}":1091666,
    "{\"element_url\":\"/\",\"elementClasses\":\"\",\"elementId\":\"\",\"elementText\":\"100%20บาท\",\"dataanalyticsID\":\"null\"}":1092106,
    "{\"element_url\":\"/\",\"elementClasses\":\"v-icon%20mdi%20mdi-magnify%20theme--dark\",\"elementId\":\"\",\"elementText\":\"\",\"dataanalyticsID\":\"null\"}":1092685,
    "{\"element_url\":\"/\",\"elementClasses\":\"resendPin%20disabled%20disabled%20requesting\",\"elementId\":\"\",\"elementText\":\"ส่งรหัสอีกครั้ง%20(25)\",\"dataanalyticsID\":\"null\"}":1092837,
    "{\"element_url\":\"/\",\"elementClasses\":\"game-image-holder\",\"elementId\":\"\",\"elementText\":\"JILI%20เล่นจริง%20BaoBoonChin\",\"dataanalyticsID\":\"null\"}":1092905,
    "{\"element_url\":\"/\",\"elementClasses\":\"v-pagination__item\",\"elementId\":\"\",\"elementText\":\"3\",\"dataanalyticsID\":\"null\"}":1093447,
    "{\"element_url\":\"/\",\"elementClasses\":\"\",\"elementId\":\"\",\"elementText\":\"Promotions\",\"dataanalyticsID\":\"null\"}":1093666,
    "{\"element_url\":\"/\",\"elementClasses\":\"\",\"elementId\":\"\",\"elementText\":\"ยอดนิยม\",\"dataanalyticsID\":\"null\"}":1093760,
    "{\"element_url\":\"/v2/SI/PictureLanguage.240.4\",\"elementClasses\":\"swiper-lazy%20swiper-lazy-loaded\",\"elementId\":\"\",\"elementText\":\"\",\"dataanalyticsID\":\"null\"}":1093791,
    "{\"element_url\":\"/v2/SI/PictureLanguage.232.4\",\"elementClasses\":\"swiper-lazy%20swiper-lazy-loaded\",\"elementId\":\"\",\"elementText\":\"\",\"dataanalyticsID\":\"null\"}":1093873,
    "{\"element_url\":\"/\",\"elementClasses\":\"resendPin%20disabled%20disabled%20requesting\",\"elementId\":\"\",\"elementText\":\"ส่งรหัสอีกครั้ง%20(29)\",\"dataanalyticsID\":\"null\"}":1094016,
    "{\"element_url\":\"/\",\"elementClasses\":\"flex%20lblChooseBank%20xs12%20sm4%20md4\",\"elementId\":\"\",\"elementText\":\"ธนาคารของคุณ\",\"dataanalyticsID\":\"null\"}":1094471,
    "{\"element_url\":\"/\",\"elementClasses\":\"game-image-holder\",\"elementId\":\"\",\"elementText\":\"CQ9%20เล่นจริง%20หรือลองดูตัวอย่าง%20jumping%20mobile\",\"dataanalyticsID\":\"null\"}":1094990,
    "{\"element_url\":\"/\",\"elementClasses\":\"_hj-qnMJa__styles__primaryButton%20_hj-caA8H__PrimaryButton__phone\",\"elementId\":\"\",\"elementText\":\"Send\",\"dataanalyticsID\":\"null\"}":1095299,
    "{\"element_url\":\"/en/Fish-Games\",\"elementClasses\":\"\",\"elementId\":\"\",\"elementText\":\"Fish%20Games\",\"dataanalyticsID\":\"null\"}":1095605,
    "{\"element_url\":\"/\",\"elementClasses\":\"game-info\",\"elementId\":\"\",\"elementText\":\"Lucky%20Neko\",\"dataanalyticsID\":\"null\"}":1095882,
    "{\"element_url\":\"/\",\"elementClasses\":\"promotionModalTitle\",\"elementId\":\"\",\"elementText\":\"ฝาก%2050%20รับฟรี%20300\",\"dataanalyticsID\":\"null\"}":1096000,
    "{\"element_url\":\"/\",\"elementClasses\":\"game-image-holder\",\"elementId\":\"\",\"elementText\":\"R88%20เล่นจริง%20Gem%20Mine\",\"dataanalyticsID\":\"null\"}":1096248,
    "{\"element_url\":\"/\",\"elementClasses\":\"noGames\",\"elementId\":\"\",\"elementText\":\"กำลังโหลดรายชื่อเกม...\",\"dataanalyticsID\":\"null\"}":1096671,
    "{\"element_url\":\"/\",\"elementClasses\":\"jwbtn%20btnJoin%20jwbtn-green\",\"elementId\":\"\",\"elementText\":\"เข้าร่วมโปรโมชั่น\",\"dataanalyticsID\":\"null\"}":1096678,
    "{\"element_url\":\"/\",\"elementClasses\":\"detailLabel%20jwText\",\"elementId\":\"\",\"elementText\":\"เกมแนะนำ\",\"dataanalyticsID\":\"null\"}":1096711,
    "{\"element_url\":\"/en/Slots\",\"elementClasses\":\"\",\"elementId\":\"\",\"elementText\":\"Slots\",\"dataanalyticsID\":\"null\"}":1096751,
    "{\"element_url\":\"/\",\"elementClasses\":\"game-image-holder\",\"elementId\":\"\",\"elementText\":\"PP%20เล่นจริง%20หรือลองดูตัวอย่าง%20Wild%20West%20Gold™️\",\"dataanalyticsID\":\"null\"}":1096896,
    "{\"element_url\":\"/\",\"elementClasses\":\"game-info\",\"elementId\":\"\",\"elementText\":\"Golden%20Empire\",\"dataanalyticsID\":\"null\"}":1097037,
    "{\"element_url\":\"/\",\"elementClasses\":\"iconWrapper%20loyaltyIcon\",\"elementId\":\"\",\"elementText\":\"\",\"dataanalyticsID\":\"null\"}":1097089,
    "{\"element_url\":\"/\",\"elementClasses\":\"codeWrapper\",\"elementId\":\"\",\"elementText\":\"กรุณาใส่หมายเลขที่คุณได้รับ%20*%20กรุณาใส่รหัสยืนยัน%20ยืนยันความถูกต้อง\",\"dataanalyticsID\":\"null\"}":1097167,
    "{\"element_url\":\"/\",\"elementClasses\":\"game-image-holder\",\"elementId\":\"\",\"elementText\":\"PG%20เล่นจริง%20Captain-singleQuotePLH-s%20Bounty\",\"dataanalyticsID\":\"null\"}":1097213,
    "{\"element_url\":\"/\",\"elementClasses\":\"text\",\"elementId\":\"\",\"elementText\":\"งดให้บริการกับธนาคาร%20KBANK-14%20(กสิกร)%20096-X-40XXX-9%20น.ส.%20พรชิตา%20สังขรัตน์%20ชั่วคราวอย่างไม่มีกำหนด\",\"dataanalyticsID\":\"null\"}":1097279,
    "{\"element_url\":\"/\",\"elementClasses\":\"\",\"elementId\":\"\",\"elementText\":\"Lucky%20Neko\",\"dataanalyticsID\":\"null\"}":1097765,
    "{\"element_url\":\"/\",\"elementClasses\":\"layout%20gameList%20row%20wrap\",\"elementId\":\"\",\"elementText\":\"PG%20เล่นจริง%20Caishen%20Wins%20PG%20เล่นจริง%20Mahjong%20Ways%202%20JILI%20เล่นจริง%20RomaX%20JILI%20เล่นจริง%20Charge%20Buffalo%20PG%20เล่นจริง%20Ways%20of%20the%20Qilin%20PG%20เล่นจริง%20Ganesha%20Fortune%20PS%20เล่นจริง%20หรือลองดูตัวอย่าง%20Super%20Powerful%20JILI%20เล่นจริง%20FortunePig%20YGG%20เล่นจริง%20Zeus%20Vs%20Thor%20JOKER%20เล่นจริง%20Roma%20JDB%20เล่นจริง%20หรือลองดูตัวอย่าง%20SuperNuibi%20JILI%20เล่นจริง%20Crazy777%20JILI%20เล่นจริง%20War%20of%20Dragons%20JDB%20เล่นจริง%20หรือลองดูตัวอย่าง%20SuperNiubiDeluxe%20RSG%20เล่นจริง%205%20Dragons%20JILI%20เล่นจริง%20Dragon%20Treasure%20JILI%20เล่นจริง%20Golden%20Empire%20JILI%20เล่นจริง%20Hot%20Chilli%20RSG%20เล่นจริง%20Magic%20Gem%20JDB%20เล่นจริง%20หรือลองดูตัวอย่าง%20Open%20Sesame%20AW%20เล่นจริง%20Beach%20Babes%20ISB%20เล่นจริง%20หรือลองดูตัวอย่าง%20Aztec%20Gold%20Megaways%20ISB%20เล่นจริง%20หรือลองดูตัวอย่าง%20Prosperity%20Ox%20ISB%20เล่นจริง%20หรือลองดูตัวอย่าง%20Merlin%20Magic%20Mirror\",\"dataanalyticsID\":\"null\"}":1097809,
    "{\"element_url\":\"/en/Messages\",\"elementClasses\":\"\",\"elementId\":\"\",\"elementText\":\"Message\",\"dataanalyticsID\":\"null\"}":1098407,
    "{\"element_url\":\"/\",\"elementClasses\":\"game-image-holder\",\"elementId\":\"\",\"elementText\":\"JILI%20เล่นจริง%20King%20Kong\",\"dataanalyticsID\":\"null\"}":1098433,
    "{\"element_url\":\"/\",\"elementClasses\":\"game-image-holder\",\"elementId\":\"\",\"elementText\":\"PG%20เล่นจริง%20Mahjong%20Ways%202\",\"dataanalyticsID\":\"null\"}":1098761,
    "{\"element_url\":\"/\",\"elementClasses\":\"\",\"elementId\":\"\",\"elementText\":\"แนะนำ\",\"dataanalyticsID\":\"null\"}":1098791,
    "{\"element_url\":\"/\",\"elementClasses\":\"v-icon%20v-tabs__icon%20v-tabs__icon--prev%20v-icon--link%20material-icons%20theme--dark\",\"elementId\":\"\",\"elementText\":\"chevron_left\",\"dataanalyticsID\":\"null\"}":1098901,
    "{\"element_url\":\"/\",\"elementClasses\":\"\",\"elementId\":\"\",\"elementText\":\"ฝ่ายบริการลูกค้า\",\"dataanalyticsID\":\"null\"}":1099056,
    "{\"element_url\":\"/\",\"elementClasses\":\"game-image-holder\",\"elementId\":\"\",\"elementText\":\"PG%20เล่นจริง%20FortuneOx\",\"dataanalyticsID\":\"null\"}":1099201,
    "{\"element_url\":\"/\",\"elementClasses\":\"game-image-holder\",\"elementId\":\"\",\"elementText\":\"PG%20เล่นจริง%20Dreams%20of%20Macau\",\"dataanalyticsID\":\"null\"}":1100045,
    "{\"element_url\":\"/\",\"elementClasses\":\"\",\"elementId\":\"\",\"elementText\":\"แจ็คพอต\",\"dataanalyticsID\":\"null\"}":1100120,
    "{\"element_url\":\"/\",\"elementClasses\":\"game-image-holder\",\"elementId\":\"\",\"elementText\":\"PP%20เล่นจริง%20หรือลองดูตัวอย่าง%20Great%20Rhino%20Megaways\",\"dataanalyticsID\":\"null\"}":1100160,
    "{\"element_url\":\"/\",\"elementClasses\":\"proTitle\",\"elementId\":\"\",\"elementText\":\"มีอะไรใหม่\",\"dataanalyticsID\":\"null\"}":1101205,
    "{\"element_url\":\"/\",\"elementClasses\":\"game-info\",\"elementId\":\"\",\"elementText\":\"Treasures%20of%20Aztec\",\"dataanalyticsID\":\"null\"}":1101539,
    "{\"element_url\":\"/\",\"elementClasses\":\"loginModal-wrapper\",\"elementId\":\"\",\"elementText\":\"เข้าสู่ระบบ%20ชื่อผู้ใช้%20รหัสผ่าน%20check_box_outline_blank%20จดจำฉัน%20ยังไม่เป็นสมาชิก?%20สมัครสมาชิก%20ลืมรหัสผ่าน?\",\"dataanalyticsID\":\"null\"}":1101865,
    "{\"element_url\":\"/\",\"elementClasses\":\"game-image-holder\",\"elementId\":\"\",\"elementText\":\"JILI%20เล่นจริง%20Monkey%20Party\",\"dataanalyticsID\":\"null\"}":1102029,
    "{\"element_url\":\"/\",\"elementClasses\":\"v-tabs__bar%20theme--dark%20transparent\",\"elementId\":\"\",\"elementText\":\"chevron_left%20All%20chevron_right\",\"dataanalyticsID\":\"null\"}":1102032,
    "{\"element_url\":\"/\",\"elementClasses\":\"wrapSetting\",\"elementId\":\"\",\"elementText\":\"\",\"dataanalyticsID\":\"null\"}":1102735,
    "{\"element_url\":\"/\",\"elementClasses\":\"toolbar-wrapper\",\"elementId\":\"\",\"elementText\":\"-RAND-%20-RAND-%20ยอดเงินของคุณดูเหมือนจะเหลือน้อย%20TH%20kuad32\",\"dataanalyticsID\":\"null\"}":1102779,
    "{\"element_url\":\"/\",\"elementClasses\":\"v-input__slot\",\"elementId\":\"\",\"elementText\":\"check_box%20จดจำฉัน\",\"dataanalyticsID\":\"null\"}":1102941,
    "{\"element_url\":\"/\",\"elementClasses\":\"v-icon%20material-icons%20theme--dark%20primary--text\",\"elementId\":\"\",\"elementText\":\"arrow_drop_down\",\"dataanalyticsID\":\"null\"}":1103550,
    "{\"element_url\":\"/\",\"elementClasses\":\"_hj-3PSb0__ExpandedWidget__innerContainer\",\"elementId\":\"\",\"elementText\":\"คุณชอบอินเทอร์เฟซใหม่ของเราหรือไม่%20Hate%20Dislike%20Neutral%20Like%20Love%20Not%20using%20Hotjar%20yet?\",\"dataanalyticsID\":\"null\"}":1103808,
    "{\"element_url\":\"/\",\"elementClasses\":\"game-info\",\"elementId\":\"\",\"elementText\":\"Ways%20of%20the%20Qilin\",\"dataanalyticsID\":\"null\"}":1103931,
    "{\"element_url\":\"/\",\"elementClasses\":\"container\",\"elementId\":\"\",\"elementText\":\"คาสิโนสด%20สล็อต%20กีฬา%20เกมตกปลา%20Crypto%20อื่นๆ%20โปรโมชั่น%20VIP\",\"dataanalyticsID\":\"null\"}":1103982,
    "{\"element_url\":\"/\",\"elementClasses\":\"platforms\",\"elementId\":\"\",\"elementText\":\"SG\",\"dataanalyticsID\":\"null\"}":1104213,
    "{\"element_url\":\"/\",\"elementClasses\":\"primaryToolbar\",\"elementId\":\"\",\"elementText\":\"*บัญชีของคุณถูกล็อค%20กรุณาติดต่อฝ่ายบริการลูกค้า%20จดจำฉัน%20ลืมรหัสผ่าน%20?%20เข้าสู่ระบบ%20สมัครสมาชิก%20TH\",\"dataanalyticsID\":\"null\"}":1104219,
    "{\"element_url\":\"/\",\"elementClasses\":\"v-dialog%20spin-win-wrapper%20v-dialog--active%20v-dialog--persistent%20v-dialog--fullscreen\",\"elementId\":\"\",\"elementText\":\"ยินดีด้วย!%20คุณมีฟรีสปิน%20หมุนเดี๋ยวนี้\",\"dataanalyticsID\":\"null\"}":1104682,
    "{\"element_url\":\"/\",\"elementClasses\":\"game-image-holder\",\"elementId\":\"\",\"elementText\":\"JDB%20เล่นจริง%20หรือลองดูตัวอย่าง%20Dragons\",\"dataanalyticsID\":\"null\"}":1104850,
    "{\"element_url\":\"/service/image/4e805c00-a357-11ec-89ce-1b58bff63e61\",\"elementClasses\":\"\",\"elementId\":\"\",\"elementText\":\"\",\"dataanalyticsID\":\"null\"}":1105220,
    "{\"element_url\":\"/\",\"elementClasses\":\"game-image-holder\",\"elementId\":\"\",\"elementText\":\"RELAX%20เล่นจริง%20หรือลองดูตัวอย่าง%20Money%20Train%202\",\"dataanalyticsID\":\"null\"}":1105372,
    "{\"element_url\":\"/\",\"elementClasses\":\"game-image-holder\",\"elementId\":\"\",\"elementText\":\"PG%20เล่นจริง%20Thai%20River%20Wonders\",\"dataanalyticsID\":\"null\"}":1105439,
    "{\"element_url\":\"/\",\"elementClasses\":\"game-image-holder\",\"elementId\":\"\",\"elementText\":\"PG%20เล่นจริง%20Fortune%20Mouse\",\"dataanalyticsID\":\"null\"}":1105642,
    "{\"element_url\":\"/\",\"elementClasses\":\"game-image-holder\",\"elementId\":\"\",\"elementText\":\"PG%20เล่นจริง%20Egypt-singleQuotePLH-s%20Book%20of%20Mystery\",\"dataanalyticsID\":\"null\"}":1105652,
    "{\"element_url\":\"/\",\"elementClasses\":\"v-icon%20fav-icon%20gameActionIcon%20v-icon--link%20mdi%20mdi-heart%20theme--dark\",\"elementId\":\"\",\"elementText\":\"\",\"dataanalyticsID\":\"null\"}":1106237,
    "{\"element_url\":\"/\",\"elementClasses\":\"labelText\",\"elementId\":\"\",\"elementText\":\"ออกจากระบบ\",\"dataanalyticsID\":\"null\"}":1106374,
    "{\"element_url\":\"/\",\"elementClasses\":\"game-image-holder\",\"elementId\":\"\",\"elementText\":\"R88%20เล่นจริง%20Guessing%20baskets\",\"dataanalyticsID\":\"null\"}":1106400,
    "{\"element_url\":\"/pn/sw/prod/platform/icon/v2/PL/1629872139331.png\",\"elementClasses\":\"platformIcon\",\"elementId\":\"\",\"elementText\":\"\",\"dataanalyticsID\":\"null\"}":1106612,
    "{\"element_url\":\"/pn/sw/prod/platform/icon/v2/EVOPLAY/icon_1629873735923.png\",\"elementClasses\":\"platformIcon\",\"elementId\":\"\",\"elementText\":\"\",\"dataanalyticsID\":\"null\"}":1106622,
    "{\"element_url\":\"/\",\"elementClasses\":\"\",\"elementId\":\"\",\"elementText\":\"Mahjong%20Ways\",\"dataanalyticsID\":\"null\"}":1106899,
    "{\"element_url\":\"/\",\"elementClasses\":\"game-image-holder\",\"elementId\":\"\",\"elementText\":\"PG%20เล่นจริง%20Jurassic%20Kingdom\",\"dataanalyticsID\":\"null\"}":1106912,
    "{\"element_url\":\"/\",\"elementClasses\":\"\",\"elementId\":\"\",\"elementText\":\"ทำเทิร์น\",\"dataanalyticsID\":\"null\"}":1107415,
    "{\"element_url\":\"/\",\"elementClasses\":\"game-image-holder\",\"elementId\":\"\",\"elementText\":\"PG%20เล่นจริง%20Win%20Win%20Won\",\"dataanalyticsID\":\"null\"}":1107569,
    "{\"element_url\":\"/\",\"elementClasses\":\"\",\"elementId\":\"\",\"elementText\":\"ทั้งหมด\",\"dataanalyticsID\":\"null\"}":1108205,
    "{\"element_url\":\"/\",\"elementClasses\":\"\",\"elementId\":\"\",\"elementText\":\"ยกเลิก\",\"dataanalyticsID\":\"null\"}":1108545,
    "{\"element_url\":\"/\",\"elementClasses\":\"\",\"elementId\":\"\",\"elementText\":\"Oriental%20Prosperity\",\"dataanalyticsID\":\"null\"}":1108637,
    "{\"element_url\":\"/\",\"elementClasses\":\"contactNav\",\"elementId\":\"\",\"elementText\":\"ติดต่อ\",\"dataanalyticsID\":\"null\"}":1108646,
    "{\"element_url\":\"/\",\"elementClasses\":\"game-image-holder\",\"elementId\":\"\",\"elementText\":\"PG%20เล่นจริง%20Spirited%20Wonders\",\"dataanalyticsID\":\"null\"}":1108747,
    "{\"element_url\":\"/pn/sw/prod/platform/icon/v2/PTO/icon_1629874533443.png\",\"elementClasses\":\"platformIcon\",\"elementId\":\"\",\"elementText\":\"\",\"dataanalyticsID\":\"null\"}":1108776,
    "{\"element_url\":\"/pn/si/web/prod/build/v1.4.84/img/07a95da.svg\",\"elementClasses\":\"logo\",\"elementId\":\"\",\"elementText\":\"\",\"dataanalyticsID\":\"null\"}":1108843,
    "{\"element_url\":\"/pn/si/web/prod/build/v1.4.84/img/174247e.svg\",\"elementClasses\":\"logo\",\"elementId\":\"\",\"elementText\":\"\",\"dataanalyticsID\":\"null\"}":1108845,
    "{\"element_url\":\"/pn/si/web/prod/build/v1.4.84/img/2ef8be5.svg\",\"elementClasses\":\"\",\"elementId\":\"\",\"elementText\":\"\",\"dataanalyticsID\":\"null\"}":1108852,
    "{\"element_url\":\"/pn/si/web/prod/build/v1.4.84/img/10d10a2.svg\",\"elementClasses\":\"\",\"elementId\":\"\",\"elementText\":\"\",\"dataanalyticsID\":\"null\"}":1108861,
    "{\"element_url\":\"/pn/si/web/prod/build/v1.4.84/img/9270d48.png\",\"elementClasses\":\"\",\"elementId\":\"\",\"elementText\":\"\",\"dataanalyticsID\":\"null\"}":1108864,
    "{\"element_url\":\"/pn/si/web/prod/build/v1.4.84/img/5954f7d.svg\",\"elementClasses\":\"iconReward\",\"elementId\":\"\",\"elementText\":\"\",\"dataanalyticsID\":\"null\"}":1108868,
    "{\"element_url\":\"/pn/si/web/prod/build/v1.4.84/img/b7c43ea.svg\",\"elementClasses\":\"logo\",\"elementId\":\"\",\"elementText\":\"\",\"dataanalyticsID\":\"null\"}":1108884,
    "{\"element_url\":\"/pn/si/web/prod/build/v1.4.84/img/5c91dd7.svg\",\"elementClasses\":\"logo\",\"elementId\":\"\",\"elementText\":\"\",\"dataanalyticsID\":\"null\"}":1108887,
    "{\"element_url\":\"/pn/si/web/prod/build/v1.4.84/img/98e92ee.svg\",\"elementClasses\":\"\",\"elementId\":\"\",\"elementText\":\"\",\"dataanalyticsID\":\"null\"}":1108918,
    "{\"element_url\":\"/pn/si/web/prod/build/v1.4.84/img/a39d72d.svg\",\"elementClasses\":\"\",\"elementId\":\"\",\"elementText\":\"\",\"dataanalyticsID\":\"null\"}":1108920,
    "{\"element_url\":\"/pn/si/web/prod/build/v1.4.84/img/823ee4a.svg\",\"elementClasses\":\"\",\"elementId\":\"\",\"elementText\":\"\",\"dataanalyticsID\":\"null\"}":1108921,
    "{\"element_url\":\"/pn/si/web/prod/build/v1.4.84/img/fe5a482.svg\",\"elementClasses\":\"\",\"elementId\":\"\",\"elementText\":\"\",\"dataanalyticsID\":\"null\"}":1109026,
    "{\"element_url\":\"/\",\"elementClasses\":\"\",\"elementId\":\"\",\"elementText\":\"ข้อกำหนดและเงื่อนไขของ%20siam99%20มีผลบังคับใช้\",\"dataanalyticsID\":\"null\"}":1109035,
    "{\"element_url\":\"/pn/si/web/prod/build/v1.4.84/img/195cadb.gif\",\"elementClasses\":\"\",\"elementId\":\"\",\"elementText\":\"\",\"dataanalyticsID\":\"null\"}":1109049,
    "{\"element_url\":\"/pn/si/web/prod/build/v1.4.84/img/98e92ee.svg\",\"elementClasses\":\"tierImage\",\"elementId\":\"\",\"elementText\":\"\",\"dataanalyticsID\":\"null\"}":1109085,
    "{\"element_url\":\"/pn/si/web/prod/build/v1.4.84/img/9bf3822.png\",\"elementClasses\":\"\",\"elementId\":\"\",\"elementText\":\"\",\"dataanalyticsID\":\"null\"}":1109092,
    "{\"element_url\":\"/\",\"elementClasses\":\"_hj-3OscV__styles__clearButton%20_hj-1baop__EmailStep__clearButton\",\"elementId\":\"\",\"elementText\":\"Skip\",\"dataanalyticsID\":\"null\"}":1109220,
    "{\"element_url\":\"/pn/si/web/prod/build/v1.4.84/img/1a19963.png\",\"elementClasses\":\"\",\"elementId\":\"\",\"elementText\":\"\",\"dataanalyticsID\":\"null\"}":1109411,
    "{\"element_url\":\"/\",\"elementClasses\":\"\",\"elementId\":\"\",\"elementText\":\"เพิ่มธนาคาร\",\"dataanalyticsID\":\"null\"}":1109417,
    "{\"element_url\":\"/pn/si/web/prod/build/v1.4.84/img/f86dcd2.png\",\"elementClasses\":\"\",\"elementId\":\"\",\"elementText\":\"\",\"dataanalyticsID\":\"null\"}":1109426,
    "{\"element_url\":\"/\",\"elementClasses\":\"game-image-holder\",\"elementId\":\"\",\"elementText\":\"SEXY%20เล่นจริง%20SEXY%20Lobby\",\"dataanalyticsID\":\"null\"}":1109881,
    "{\"element_url\":\"/\",\"elementClasses\":\"resendPin%20disabled%20disabled%20requesting\",\"elementId\":\"\",\"elementText\":\"ส่งรหัสอีกครั้ง%20(16)\",\"dataanalyticsID\":\"null\"}":1109982,
    "{\"element_url\":\"/pn/si/web/prod/build/v1.4.84/img/159cc37.png\",\"elementClasses\":\"\",\"elementId\":\"\",\"elementText\":\"\",\"dataanalyticsID\":\"null\"}":1110032,
    "{\"element_url\":\"/\",\"elementClasses\":\"errorList\",\"elementId\":\"\",\"elementText\":\"*%20คุณมียอดเงินไม่เพียงพอ\",\"dataanalyticsID\":\"null\"}":1110052,
    "{\"element_url\":\"/\",\"elementClasses\":\"v-dialog%20loginModal%20v-dialog--active%20v-dialog--persistent\",\"elementId\":\"\",\"elementText\":\"เข้าสู่ระบบ%20ชื่อผู้ใช้%20รหัสผ่าน%20check_box_outline_blank%20จดจำฉัน%20เข้าสู่ระบบ%20ยังไม่เป็นสมาชิก?%20สมัครสมาชิก%20ลืมรหัสผ่าน?\",\"dataanalyticsID\":\"null\"}":1110604,
    "{\"element_url\":\"/pn/sw/prod/platform/icon/v2/FC/icon_1629873138478.png\",\"elementClasses\":\"platformIcon\",\"elementId\":\"\",\"elementText\":\"\",\"dataanalyticsID\":\"null\"}":1112054,
    "{\"element_url\":\"/\",\"elementClasses\":\"game-image-holder\",\"elementId\":\"\",\"elementText\":\"PG%20เล่นจริง%20Lucky%20Neko\",\"dataanalyticsID\":\"null\"}":1112080,
    "{\"element_url\":\"/v2/SI/PromotionInfoLanguage2740\",\"elementClasses\":\"\",\"elementId\":\"\",\"elementText\":\"\",\"dataanalyticsID\":\"null\"}":1112677,
    "{\"element_url\":\"/\",\"elementClasses\":\"loginModal-wrapper\",\"elementId\":\"\",\"elementText\":\"เข้าสู่ระบบ%20ชื่อผู้ใช้%20รหัสผ่าน%20check_box%20จดจำฉัน%20ยังไม่เป็นสมาชิก?%20สมัครสมาชิก%20ลืมรหัสผ่าน?\",\"dataanalyticsID\":\"null\"}":1112848,
    "{\"element_url\":\"/pn/si/web/prod/build/v1.4.84/img/500183d.svg\",\"elementClasses\":\"noGames\",\"elementId\":\"\",\"elementText\":\"\",\"dataanalyticsID\":\"null\"}":1113413,
    "{\"element_url\":\"/\",\"elementClasses\":\"container%20gameListWrapper%20grid-list-cs\",\"elementId\":\"\",\"elementText\":\"PG%20เล่นจริง%20Caishen%20Wins%20PG%20เล่นจริง%20Mahjong%20Ways%202%20PG%20เล่นจริง%20Ways%20of%20the%20Qilin%20PG%20เล่นจริง%20Ganesha%20Fortune%20PG%20เล่นจริง%20Treasures%20of%20Aztec%20PG%20เล่นจริง%20Wild%20Fireworks%20PG%20เล่นจริง%20Lucky%20Neko%20PG%20เล่นจริง%20Mahjong%20Ways%20PG%20เล่นจริง%20Egypt-singleQuotePLH-s%20Book%20of%20Mystery%20PG%20เล่นจริง%20Dragon%20Hatch%20PG%20เล่นจริง%20Fortune%20Mouse%20PG%20เล่นจริง%20Jurassic%20Kingdom%20PG%20เล่นจริง%20Dreams%20of%20Macau%20PG%20เล่นจริง%20Captain-singleQuotePLH-s%20Bounty%20PG%20เล่นจริง%20The%20Great%20Icescape%20PG%20เล่นจริง%20Leprechaun%20Riches%20PG%20เล่นจริง%20Wild%20Bandito%20PG%20เล่นจริง%20Ganesha%20Gold%20PG%20เล่นจริง%20FortuneOx%20PG%20เล่นจริง%20Double%20Fortune%20PG%20เล่นจริง%20Candy%20Burst%20PG%20เล่นจริง%20Muay%20Thai%20Champion%20PG%20เล่นจริง%20Queen%20of%20Bounty%20PG%20เล่นจริง%20Shaolin%20Soccer%20Load%20More%20Games\",\"dataanalyticsID\":\"null\"}":1114182,
    "{\"element_url\":\"/\",\"elementClasses\":\"game-image-holder\",\"elementId\":\"\",\"elementText\":\"FC%20เล่นจริง%20MONEY%20TREE%20DOZER\",\"dataanalyticsID\":\"null\"}":1115134,
    "{\"element_url\":\"/\",\"elementClasses\":\"promoModalWrapper\",\"elementId\":\"\",\"elementText\":\"\",\"dataanalyticsID\":\"null\"}":1115466,
    "{\"element_url\":\"/\",\"elementClasses\":\"\",\"elementId\":\"\",\"elementText\":\"หมุนและชนะ\",\"dataanalyticsID\":\"null\"}":1115734,
    "{\"element_url\":\"/v2/SI/PictureLanguage.272.4\",\"elementClasses\":\"swiper-lazy%20swiper-lazy-loaded\",\"elementId\":\"\",\"elementText\":\"\",\"dataanalyticsID\":\"null\"}":1116391,
    "{\"element_url\":\"/\",\"elementClasses\":\"game-image-holder\",\"elementId\":\"\",\"elementText\":\"MGP%20เล่นจริง%20Lucky%20Twins\",\"dataanalyticsID\":\"null\"}":1116727,
    "{\"element_url\":\"/\",\"elementClasses\":\"promoCardWrapper\",\"elementId\":\"\",\"elementText\":\"ใส่จำนวนเงิน:%20*%20คุณมียอดเงินไม่เพียงพอ%20โบนัส:%20300%20เทิร์นโอเวอร์:%208750%20เข้าร่วมโปรโมชั่น\",\"dataanalyticsID\":\"null\"}":1116756,
    "{\"element_url\":\"/\",\"elementClasses\":\"game-image-holder\",\"elementId\":\"\",\"elementText\":\"JILI%20เล่นจริง%20Boxing%20King\",\"dataanalyticsID\":\"null\"}":1116915,
    "{\"element_url\":\"/\",\"elementClasses\":\"\",\"elementId\":\"\",\"elementText\":\"“เพิ่มความสนุกและลุ้นรับรางวัลที่น่าตื่นตาตื่นใจ”\",\"dataanalyticsID\":\"null\"}":1117083,
    "{\"element_url\":\"/\",\"elementClasses\":\"\",\"elementId\":\"\",\"elementText\":\"Treasures%20of%20Aztec\",\"dataanalyticsID\":\"null\"}":1117344,
    "{\"element_url\":\"/\",\"elementClasses\":\"game-info\",\"elementId\":\"\",\"elementText\":\"Mahjong%20Ways\",\"dataanalyticsID\":\"null\"}":1118419,
    "{\"element_url\":\"/\",\"elementClasses\":\"jwbtn%20jwbtn-white%20copy-link\",\"elementId\":\"\",\"elementText\":\"คัดลอกลิงค์แล้ว\",\"dataanalyticsID\":\"null\"}":1118712,
    "{\"element_url\":\"/\",\"elementClasses\":\"v-list__tile__content\",\"elementId\":\"\",\"elementText\":\"กสิกรไทย%20(KBANK)\",\"dataanalyticsID\":\"null\"}":1119208,
    "{\"element_url\":\"/\",\"elementClasses\":\"game-image-holder\",\"elementId\":\"\",\"elementText\":\"PP%20เล่นจริง%20หรือลองดูตัวอย่าง%20Dance%20Party\",\"dataanalyticsID\":\"null\"}":1119316,
    "{\"element_url\":\"/\",\"elementClasses\":\"v-content__wrap\",\"elementId\":\"\",\"elementText\":\"ทั้งหมด%20แนะนำ%20ยอดนิยม%20แจ็คพอต%20ใหม่%20เล่นเพื่อความสนุก%20chevron_left%20All%20chevron_right%20PG%20เล่นจริง%20Caishen%20Wins%20PG%20เล่นจริง%20Mahjong%20Ways%202%20PG%20เล่นจริง%20Ways%20of%20the%20Qilin%20PG%20เล่นจริง%20Ganesha%20Fortune%20PG%20เล่นจริง%20Treasures%20of%20Aztec%20PG%20เล่นจริง%20Wild%20Fireworks%20PG%20เล่นจริง%20Lucky%20Neko%20PG%20เล่นจริง%20Mahjong%20Ways%20PG%20เล่นจริง%20Egypt-singleQuotePLH-s%20Book%20of%20Mystery%20PG%20เล่นจริง%20Dragon%20Hatch%20PG%20เล่นจริง%20Fortune%20Mouse%20PG%20เล่นจริง%20Jurassic%20Kingdom%20PG%20เล่นจริง%20Dreams%20of%20Macau%20PG%20เล่นจริง%20Captain-singleQuotePLH-s%20Bounty%20PG%20เล่นจริง%20The%20Great%20Icescape%20PG%20เล่นจริง%20Leprechaun%20Riches%20PG%20เล่นจริง%20Wild%20Bandito%20PG%20เล่นจริง%20Ganesha%20Gold%20PG%20เล่นจริง%20FortuneOx%20PG%20เล่นจริง%20Double%20Fortune%20PG%20เล่นจริง%20Candy%20Burst%20PG%20เล่นจริง%20Muay%20Thai%20Champion%20PG%20เล่นจริง%20Queen%20of%20Bounty%20PG%20เล่นจริง%20Shaolin%20Soccer%20Load%20More%20Games\",\"dataanalyticsID\":\"null\"}":1119782,
    "{\"element_url\":\"/pn/sw/prod/platform/icon/v2/PS/icon_1629873833856.png\",\"elementClasses\":\"platformIcon\",\"elementId\":\"\",\"elementText\":\"\",\"dataanalyticsID\":\"null\"}":1120938,
    "{\"element_url\":\"/pn/sw/prod/platform/icon/v2/SG/icon_1629872749599.png\",\"elementClasses\":\"platformIcon\",\"elementId\":\"\",\"elementText\":\"\",\"dataanalyticsID\":\"null\"}":1122434,
    "{\"element_url\":\"/\",\"elementClasses\":\"downloadApp\",\"elementId\":\"\",\"elementText\":\"ดาวน์โหลดแอพ\",\"dataanalyticsID\":\"null\"}":1123011,
    "{\"element_url\":\"/pn/sw/prod/platform/icon/v2/JILI/icon_1629873000145.png\",\"elementClasses\":\"platformIcon\",\"elementId\":\"\",\"elementText\":\"\",\"dataanalyticsID\":\"null\"}":1123069,
    "{\"element_url\":\"/pn/sw/prod/platform/icon/v2/MGP/icon_1629873021283.png\",\"elementClasses\":\"platformIcon\",\"elementId\":\"\",\"elementText\":\"\",\"dataanalyticsID\":\"null\"}":1123070,
    "{\"element_url\":\"/pn/sw/prod/platform/icon/v2/R88/icon_1629874635139.png\",\"elementClasses\":\"platformIcon\",\"elementId\":\"\",\"elementText\":\"\",\"dataanalyticsID\":\"null\"}":1123074,
    "{\"element_url\":\"/pn/sw/prod/platform/icon/v2/RELAX/icon_1632903433460.png\",\"elementClasses\":\"platformIcon\",\"elementId\":\"\",\"elementText\":\"\",\"dataanalyticsID\":\"null\"}":1123081,
    "{\"element_url\":\"/pn/sw/prod/platform/icon/v2/JOKER/icon_1629874587901.png\",\"elementClasses\":\"platformIcon\",\"elementId\":\"\",\"elementText\":\"\",\"dataanalyticsID\":\"null\"}":1123082,
    "{\"element_url\":\"/\",\"elementClasses\":\"\",\"elementId\":\"\",\"elementText\":\"Ways%20of%20the%20Qilin\",\"dataanalyticsID\":\"null\"}":1123452,
    "{\"element_url\":\"/\",\"elementClasses\":\"v-tabs__item\",\"elementId\":\"\",\"elementText\":\"เหตุการณ์\",\"dataanalyticsID\":\"null\"}":1124228,
    "{\"element_url\":\"/\",\"elementClasses\":\"v-tabs__item%20v-tabs__item--active\",\"elementId\":\"\",\"elementText\":\"เหตุการณ์\",\"dataanalyticsID\":\"null\"}":1124229,
    "{\"element_url\":\"/\",\"elementClasses\":\"_hj-wTRLt__Title__Title%20_hj-1f7kP__Title__phone\",\"elementId\":\"email-label\",\"elementText\":\"We%20may%20wish%20to%20follow%20up.%20Enter%20your%20email%20if%20you-singleQuotePLH-re%20happy%20for%20us%20to%20contact%20you.\",\"dataanalyticsID\":\"null\"}":1124368,
    "{\"element_url\":\"/\",\"elementClasses\":\"content-wrapper%20content-referral-wrapper\",\"elementId\":\"\",\"elementText\":\"Referral%20Id:%20araya2019%20สร้างบัญชีบน%20Siam99%20เพื่อเล่นเกมออนไลน์ที่น่าตื่นเต้นทั้งหมด%20ไม่มีข้อจำกัด%20ฟรี%20กรุณากรอกแบบฟอร์มสมัรสมาชิกด้านล่าง%20ชื่อผู้ใช้%20รหัสผ่าน%20ยืนยันรหัสผ่าน%20ชื่อ-นามสกุล%20อีเมล%20เบอร์มือถือ%20รหัสรักษาความปลอดภัย%20สมัครสมาชิก\",\"dataanalyticsID\":\"null\"}":1125203,
    "{\"element_url\":\"/\",\"elementClasses\":\"forgotModal-wrapper\",\"elementId\":\"\",\"elementText\":\"ลืมรหัสผ่าน%20ชื่อผู้ใช้%20login.forgotPass.notify.p%20radio_button_checked%20login.forgotPass.notify.email%20radio_button_unchecked%20login.forgotPass.notify.sms%20อีเมล%20รหัสผ้องกัน%20*%20จำเป็นต้อง%20ยืนยัน\",\"dataanalyticsID\":\"null\"}":1125327,
    "{\"element_url\":\"/\",\"elementClasses\":\"referral-code\",\"elementId\":\"\",\"elementText\":\"Referral%20Id:%20araya2019\",\"dataanalyticsID\":\"null\"}":1125487,
    "{\"element_url\":\"/\",\"elementClasses\":\"game-image-holder\",\"elementId\":\"\",\"elementText\":\"RSG%20เล่นจริง%20God%20of%20Wealth\",\"dataanalyticsID\":\"null\"}":1126573,
    "{\"element_url\":\"/pn/sw/prod/platform/icon/v2/AG/1629872081817.png\",\"elementClasses\":\"platformIcon\",\"elementId\":\"\",\"elementText\":\"\",\"dataanalyticsID\":\"null\"}":1127035,
    "{\"element_url\":\"/\",\"elementClasses\":\"layout%20gameList%20row%20wrap\",\"elementId\":\"\",\"elementText\":\"HOTG%20เล่นจริง%20หรือลองดูตัวอย่าง%20lobby\",\"dataanalyticsID\":\"null\"}":1127160,
    "{\"element_url\":\"/pn/sw/prod/platform/icon/v2/PP/icon_1629873277287.png\",\"elementClasses\":\"platformIcon\",\"elementId\":\"\",\"elementText\":\"\",\"dataanalyticsID\":\"null\"}":1128328,
    "{\"element_url\":\"/\",\"elementClasses\":\"game-image-holder\",\"elementId\":\"\",\"elementText\":\"PP%20เล่นจริง%20หรือลองดูตัวอย่าง%20Sweet%20Bonanza\",\"dataanalyticsID\":\"null\"}":1128354,
    "{\"element_url\":\"/\",\"elementClasses\":\"\",\"elementId\":\"\",\"elementText\":\"Bull%20in%20a%20China%20Shop\",\"dataanalyticsID\":\"null\"}":1128368,
    "{\"element_url\":\"/\",\"elementClasses\":\"platformwrap\",\"elementId\":\"\",\"elementText\":\"AW\",\"dataanalyticsID\":\"null\"}":1128467,
    "{\"element_url\":\"/pn/sw/prod/platform/icon/v2/CQ9/icon_1629872845958.png\",\"elementClasses\":\"platformIcon\",\"elementId\":\"\",\"elementText\":\"\",\"dataanalyticsID\":\"null\"}":1128496,
    "{\"element_url\":\"/\",\"elementClasses\":\"inputAmount\",\"elementId\":\"\",\"elementText\":\"ใส่จำนวนเงิน:%20*%20คุณมียอดเงินไม่เพียงพอ\",\"dataanalyticsID\":\"null\"}":1128952,
    "{\"element_url\":\"/\",\"elementClasses\":\"game-image-holder\",\"elementId\":\"\",\"elementText\":\"JILI%20เล่นจริง%20Bubble%20Beauty\",\"dataanalyticsID\":\"null\"}":1129373,
    "{\"element_url\":\"/\",\"elementClasses\":\"application%20theme--dark\",\"elementId\":\"app\",\"elementText\":\"กรุณาใส่ชื่อเต็มของคุณ.%20จะต้องเหมือนกับชื่อเจ้าของบัญชีธนาคารของคุณ%20มิฉะนั้นการฝากเงินจะถูกปฏิเสธ%20เข้าสู่ระบบ%20สมัครสมาชิก%20TH%20คาสิโนสด%20สล็อต%20กีฬา%20เกมตกปลา%20Crypto%20อื่นๆ%20Referral%20Id:%200806912423%20สร้างบัญชีบน%20Siam99%20เพื่อเล่นเกมออนไลน์ที่น่าตื่นเต้นทั้งหมด%20ไม่มีข้อจำกัด%20ฟรี%20กรุณากรอกแบบฟอร์มสมัรสมาชิกด้านล่าง%20ชื่อผู้ใช้%20รหัสผ่าน%20ยืนยันรหัสผ่าน%20ชื่อ-นามสกุล%20อีเมล%20เบอร์มือถือ%20รหัสรักษาความปลอดภัย%20สมัครสมาชิก%20บ้าน%20โปรโมชั่น%20ฝาก%20ข่าวสาร\",\"dataanalyticsID\":\"null\"}":1129431,
    "{\"element_url\":\"/\",\"elementClasses\":\"v-list__tile__title\",\"elementId\":\"\",\"elementText\":\"กรุงไทย%20(KTB)\",\"dataanalyticsID\":\"null\"}":1129460,
    "{\"element_url\":\"/\",\"elementClasses\":\"game-name\",\"elementId\":\"\",\"elementText\":\"RomaX\",\"dataanalyticsID\":\"null\"}":1129577,
    "{\"element_url\":\"/pn/sw/prod/platform/icon/v2/BP/icon_1629874661059.png\",\"elementClasses\":\"platformIcon\",\"elementId\":\"\",\"elementText\":\"\",\"dataanalyticsID\":\"null\"}":1129612,
    "{\"element_url\":\"/pn/sw/prod/platform/icon/v2/BNG/1629872107719.png\",\"elementClasses\":\"platformIcon\",\"elementId\":\"\",\"elementText\":\"\",\"dataanalyticsID\":\"null\"}":1129624,
    "{\"element_url\":\"/\",\"elementClasses\":\"titleLabel\",\"elementId\":\"\",\"elementText\":\"RSG%20Game%20ปิดปรับปรุงกระทันหัน%20:\",\"dataanalyticsID\":\"null\"}":1129794,
    "{\"element_url\":\"/\",\"elementClasses\":\"_hj-3PSb0__ExpandedWidget__innerContainer\",\"elementId\":\"\",\"elementText\":\"We%20may%20wish%20to%20follow%20up.%20Enter%20your%20email%20if%20you-singleQuotePLH-re%20happy%20for%20us%20to%20contact%20you.%20SkipSend\",\"dataanalyticsID\":\"null\"}":1129807,
    "{\"element_url\":\"/\",\"elementClasses\":\"wf-roboto-n4-active%20wf-teko-n4-active%20wf-sarabun-n4-active%20wf-active\",\"elementId\":\"\",\"elementText\":\"\",\"dataanalyticsID\":\"null\"}":1130035,
    "{\"element_url\":\"/\",\"elementClasses\":\"application--wrap\",\"elementId\":\"\",\"elementText\":\"เข้าสู่ระบบ%20สมัครสมาชิก%20TH%20คาสิโนสด%20สล็อต%20กีฬา%20เกมตกปลา%20Crypto%20อื่นๆ%20กำลังโหลดรายละเอียดโปรโมชั่น%20...\",\"dataanalyticsID\":\"null\"}":1130071,
    "{\"element_url\":\"/\",\"elementClasses\":\"\",\"elementId\":\"\",\"elementText\":\"Money%20Coming\",\"dataanalyticsID\":\"null\"}":1131050,
    "{\"element_url\":\"/\",\"elementClasses\":\"v-progress-circular__info\",\"elementId\":\"\",\"elementText\":\"\",\"dataanalyticsID\":\"null\"}":1131114,
    "{\"element_url\":\"/\",\"elementClasses\":\"ruletitle\",\"elementId\":\"\",\"elementText\":\"2.%20Reach%20Turnover%20Per%20Day\",\"dataanalyticsID\":\"null\"}":1131328,
    "{\"element_url\":\"/\",\"elementClasses\":\"profileWrapper\",\"elementId\":\"\",\"elementText\":\"Keng282530%20Elite\",\"dataanalyticsID\":\"null\"}":1131556,
    "{\"element_url\":\"/\",\"elementClasses\":\"codeWrapper\",\"elementId\":\"\",\"elementText\":\"กรุณาใส่หมายเลขที่คุณได้รับ%20*%20ต้องเป็นตัวเลข%206%20หลัก%20ยืนยันความถูกต้อง\",\"dataanalyticsID\":\"null\"}":1132068,
    "{\"element_url\":\"/\",\"elementClasses\":\"nuxt-link-active\",\"elementId\":\"\",\"elementText\":\"Siam99\",\"dataanalyticsID\":\"null\"}":1132555,
    "{\"element_url\":\"/\",\"elementClasses\":\"v-tabs\",\"elementId\":\"\",\"elementText\":\"ทั้งหมด%20ฝาก%20ฟรีเครดิต%20กีฬา%20คาสิโนสด%20โบนัสต้อนรับ%20เงินคืน%20เหตุการณ์%20สล็อต%20เกมยิงปลา%20เข้าร่วมโปรโมชั่น%20โบนัสเงินฝากรายวัน%205%%20เข้าร่วมโปรโมชั่น%20โปรใหม่ให้โชค%20150%%20เข้าร่วมโปรโมชั่น%20โบนัสเงินฝากรายวัน%2050%%20Sexy%20Friday%20เข้าร่วมโปรโมชั่น%20โบนัสต้อนรับ%20100%%20สล็อต%20เข้าร่วมโปรโมชั่น%20โบนัสต้อนรับ%20100%%20ที่เกมยิงปลา%20เข้าร่วมโปรโมชั่น%20โบนัสเติมเงินรายวัน%2020%%20เกมตกปลา%20เข้าร่วมโปรโมชั่น%20ฝาก%20100%20รับฟรี%20200%20เฉพาะค่ายเกม%20JILI%20เข้าร่วมโปรโมชั่น%20ฝาก%2050%20รับฟรี%20300\",\"dataanalyticsID\":\"null\"}":1132705,
    "{\"element_url\":\"/\",\"elementClasses\":\"\",\"elementId\":\"\",\"elementText\":\"-RAND-%20-RAND-%20ยอดเงินของคุณดูเหมือนจะเหลือน้อย%20TH%20kuad32\",\"dataanalyticsID\":\"null\"}":1133477
}